digital_clk/mux_logic.v
module mux(
    input clk,
    input reset,
    input refstart,
    input [6:0] seg_sec_once,
    input [6:0] seg_sec_tens,
    input [6:0] seg_min_once,
    input [6:0] seg_min_tens,
    output reg [6:0] seg,
    output reg [3:0] digit
);
reg [1:0] digit_sel;
always @(posedge clk)
begin
    if (reset)
    begin
        digit_sel <= 0;
    end
    else if (refstart)
    begin
        digit_sel <= digit_sel + 1'b1;
    end
end
always @(*)
begin
    case (digit_sel)
        2'b00:
        begin
            digit = 4'b0001;
            seg = seg_min_tens;
        end

        2'b01:
        begin
            digit = 4'b0010;
            seg = seg_min_once;
        end

        2'b10:
        begin
            digit = 4'b0100;
            seg = seg_sec_tens;
        end

        2'b11:
        begin
            digit = 4'b1000;
            seg = seg_sec_once;
        end
        default:
        begin
            digit = 4'b1111;
            seg = 7'b1111111;
        end
    endcase
end
endmodule

digital_clk/seven_segment.v
module sevenseg(input [3:0]data,output reg[6:0]seg);
always@(*)begin
case(data)
4'd0:seg=7'b0000001;
4'd1:seg=7'b1111001;
4'd2:seg=7'b0100100;
4'd3:seg=7'b0110000;
4'd4:seg=7'b0011001;
4'd5:seg=7'b0010010;
4'd6:seg=7'b0000010;
4'd7:seg=7'b1111000;
4'd8:seg=7'b0000000;
4'd9:seg=7'b0010000;
default:seg=7'b1111111;
endcase
end
endmodule

digital_clk/digitsplit.v
module digitsplit(
    input [5:0] min,
    input [5:0] sec,

    output reg [3:0] min_tens,
    output reg [3:0] min_ones,
    output reg [3:0] sec_tens,
    output reg [3:0] sec_ones
);

always @(*)
begin
    min_tens = min / 10;
    min_ones = min % 10;

    sec_tens = sec / 10;
    sec_ones = sec % 10;
end

endmodule

digital_clk/digital_clk.v
module digital_clk(input clk,reset,tick,output reg [5:0]sec,min);

always@(posedge clk or posedge reset)
begin
if(reset)begin
sec<=0;
min<=0;
end
else if(tick)begin
if(sec==59)begin
sec<=0;
if(min == 59)
min<=0;
else 
min<=min+1'b1;
end
else begin
sec<=sec+1'b1;
end
end
end
endmodule

digital_clk/clkdiv.v
module clkdiv(
input clk,reset,
output reg tick,refstart);
reg [31:0]count;
reg [15:0]refcount;
always@(posedge clk)begin
if (reset)begin
tick <= 0;
count <= 0;
end
else if(count == 10)begin
tick <= 1;
count <= 0;
end

else begin
count <= count+1'b1;
tick <= 0;
end
end

always@(posedge clk)begin
if(reset)begin
refstart <= 0;
refcount <= 0;
end
else if(refcount == 5)begin
refstart <= 1;
refcount <= 0;
end
else begin
refcount <= refcount+1'b1;
refstart <= 0;
end
end
endmodule

digital_clk/topmodule.v
module Topmodule(
    input clk,
    input reset,
    output [3:0] digit,
    output [6:0] seg
);
wire tick;
wire refstart;
wire [5:0] min;
wire [5:0] sec;
wire [3:0] mintens;
wire [3:0] minones;
wire [3:0] sectens;
wire [3:0] secones;
wire [6:0] seg_min_tens;
wire [6:0] seg_min_ones;
wire [6:0] seg_sec_tens;
wire [6:0] seg_sec_ones;
clkdiv u1 (
    .clk(clk),
    .reset(reset),
    .tick(tick),
    .refstart(refstart)
);
digital_clk u2 (
    .clk(clk),
    .reset(reset),
    .tick(tick),
    .min(min),
    .sec(sec)
);
digitsplit u3 (
    .min(min),
    .sec(sec),
    .min_tens(mintens),
    .min_ones(minones),
    .sec_tens(sectens),
    .sec_ones(secones)
);
sevenseg d1(.data(mintens),.seg(seg_min_tens));
sevenseg d2(.data(minones),.seg(seg_min_ones));
sevenseg d3(.data(sectens),.seg(seg_sec_tens));
sevenseg d4(.data(secones),.seg(seg_sec_ones));

mux u4 (
    .clk(clk),
    .reset(reset),
    .refstart(refstart),
    .seg_min_tens(seg_min_tens),
    .seg_min_once(seg_min_ones),
    .seg_sec_tens(seg_sec_tens),
    .seg_sec_once(seg_sec_ones),
    .seg(seg),
    .digit(digit)
);

endmodule

digital_clk/tb.v
module testbench;

reg clk;
reg rst;
wire [6:0] seg;
wire [3:0] digit;

Topmodule uut(
    .clk(clk),
    .reset(rst),
    .seg(seg),
    .digit(digit)
);

always #10 clk = ~clk;

initial begin
    clk = 0;
    rst = 0;

    #20;
    rst = 1;

    #20;
    rst = 0;

    #200000;
    $finish;
end

initial begin
    $monitor("time=%0t rst=%b min=%0d sec=%0d",
             $time, rst, uut.min, uut.sec);

    $dumpfile("digital_clk.vcd");
    $dumpvars(0, testbench);
end

endmodule

digital_clk/digital_clk.vcd
$date
	Wed Sep 16 11:41:11 2026
$end
$version
	Icarus Verilog
$end
$timescale
	1s
$end
$scope module testbench $end
$var wire 7 ! seg [6:0] $end
$var wire 4 " digit [3:0] $end
$var reg 1 # clk $end
$var reg 1 $ rst $end
$scope module uut $end
$var wire 1 # clk $end
$var wire 1 $ reset $end
$var wire 1 % tick $end
$var wire 7 & seg_sec_tens [6:0] $end
$var wire 7 ' seg_sec_ones [6:0] $end
$var wire 7 ( seg_min_tens [6:0] $end
$var wire 7 ) seg_min_ones [6:0] $end
$var wire 7 * seg [6:0] $end
$var wire 4 + sectens [3:0] $end
$var wire 4 , secones [3:0] $end
$var wire 6 - sec [5:0] $end
$var wire 1 . refstart $end
$var wire 4 / mintens [3:0] $end
$var wire 4 0 minones [3:0] $end
$var wire 6 1 min [5:0] $end
$var wire 4 2 digit [3:0] $end
$scope module d1 $end
$var wire 4 3 data [3:0] $end
$var reg 7 4 seg [6:0] $end
$upscope $end
$scope module d2 $end
$var wire 4 5 data [3:0] $end
$var reg 7 6 seg [6:0] $end
$upscope $end
$scope module d3 $end
$var wire 4 7 data [3:0] $end
$var reg 7 8 seg [6:0] $end
$upscope $end
$scope module d4 $end
$var wire 4 9 data [3:0] $end
$var reg 7 : seg [6:0] $end
$upscope $end
$scope module u1 $end
$var wire 1 # clk $end
$var wire 1 $ reset $end
$var reg 32 ; count [31:0] $end
$var reg 16 < refcount [15:0] $end
$var reg 1 . refstart $end
$var reg 1 % tick $end
$upscope $end
$scope module u2 $end
$var wire 1 # clk $end
$var wire 1 $ reset $end
$var wire 1 % tick $end
$var reg 6 = min [5:0] $end
$var reg 6 > sec [5:0] $end
$upscope $end
$scope module u3 $end
$var wire 6 ? min [5:0] $end
$var wire 6 @ sec [5:0] $end
$var reg 4 A min_ones [3:0] $end
$var reg 4 B min_tens [3:0] $end
$var reg 4 C sec_ones [3:0] $end
$var reg 4 D sec_tens [3:0] $end
$upscope $end
$scope module u4 $end
$var wire 1 # clk $end
$var wire 1 . refstart $end
$var wire 1 $ reset $end
$var wire 7 E seg_min_once [6:0] $end
$var wire 7 F seg_min_tens [6:0] $end
$var wire 7 G seg_sec_once [6:0] $end
$var wire 7 H seg_sec_tens [6:0] $end
$var reg 4 I digit [3:0] $end
$var reg 2 J digit_sel [1:0] $end
$var reg 7 K seg [6:0] $end
$upscope $end
$upscope $end
$upscope $end
$enddefinitions $end
$comment Show the parameter values. $end
$dumpall
$end
#0
$dumpvars
bx K
bx J
bx I
bx H
bx G
bx F
bx E
bx D
bx C
bx B
bx A
bx @
bx ?
bx >
bx =
bx <
bx ;
bx :
bx 9
bx 8
bx 7
bx 6
bx 5
bx 4
bx 3
bx 2
bx 1
bx 0
bx /
x.
bx -
bx ,
bx +
bx *
bx )
bx (
bx '
bx &
x%
0$
0#
bx "
bx !
$end
#10
0%
0.
1#
#20
b1111111 !
b1111111 *
b1111111 K
b1111 "
b1111 2
b1111 I
b1 '
b1 :
b1 G
b1 &
b1 8
b1 H
b1 )
b1 6
b1 E
b1 (
b1 4
b1 F
b0 ,
b0 9
b0 C
b0 +
b0 7
b0 D
b0 0
b0 5
b0 A
b0 /
b0 3
b0 B
b0 1
b0 =
b0 ?
b0 -
b0 >
b0 @
0#
1$
#30
b1 !
b1 *
b1 K
b1 "
b1 2
b1 I
b0 J
b0 <
b0 ;
1#
#40
0#
0$
#50
b1 ;
b1 <
1#
#60
0#
#70
b10 <
b10 ;
1#
#80
0#
#90
b11 ;
b11 <
1#
#100
0#
#110
b100 <
b100 ;
1#
#120
0#
#130
b101 ;
b101 <
1#
#140
0#
#150
b0 <
1.
b110 ;
1#
#160
0#
#170
b10 "
b10 2
b10 I
b111 ;
0.
b1 <
b1 J
1#
#180
0#
#190
b10 <
b1000 ;
1#
#200
0#
#210
b1001 ;
b11 <
1#
#220
0#
#230
b100 <
b1010 ;
1#
#240
0#
#250
b0 ;
1%
b101 <
1#
#260
0#
#270
b1111001 '
b1111001 :
b1111001 G
b1 ,
b1 9
b1 C
b0 <
1.
0%
b1 ;
b1 -
b1 >
b1 @
1#
#280
0#
#290
b100 "
b100 2
b100 I
b10 ;
0.
b1 <
b10 J
1#
#300
0#
#310
b10 <
b11 ;
1#
#320
0#
#330
b100 ;
b11 <
1#
#340
0#
#350
b100 <
b101 ;
1#
#360
0#
#370
b110 ;
b101 <
1#
#380
0#
#390
b0 <
1.
b111 ;
1#
#400
0#
#410
b1111001 !
b1111001 *
b1111001 K
b1000 "
b1000 2
b1000 I
b1000 ;
0.
b1 <
b11 J
1#
#420
0#
#430
b10 <
b1001 ;
1#
#440
0#
#450
b1010 ;
b11 <
1#
#460
0#
#470
b100 <
b0 ;
1%
1#
#480
0#
#490
b100100 !
b100100 *
b100100 K
b100100 '
b100100 :
b100100 G
b10 ,
b10 9
b10 C
0%
b1 ;
b101 <
b10 -
b10 >
b10 @
1#
#500
0#
#510
b0 <
1.
b10 ;
1#
#520
0#
#530
b1 !
b1 *
b1 K
b1 "
b1 2
b1 I
b11 ;
0.
b1 <
b0 J
1#
#540
0#
#550
b10 <
b100 ;
1#
#560
0#
#570
b101 ;
b11 <
1#
#580
0#
#590
b100 <
b110 ;
1#
#600
0#
#610
b111 ;
b101 <
1#
#620
0#
#630
b0 <
1.
b1000 ;
1#
#640
0#
#650
b10 "
b10 2
b10 I
b1001 ;
0.
b1 <
b1 J
1#
#660
0#
#670
b10 <
b1010 ;
1#
#680
0#
#690
b0 ;
1%
b11 <
1#
#700
0#
#710
b110000 '
b110000 :
b110000 G
b11 ,
b11 9
b11 C
b100 <
0%
b1 ;
b11 -
b11 >
b11 @
1#
#720
0#
#730
b10 ;
b101 <
1#
#740
0#
#750
b0 <
1.
b11 ;
1#
#760
0#
#770
b100 "
b100 2
b100 I
b100 ;
0.
b1 <
b10 J
1#
#780
0#
#790
b10 <
b101 ;
1#
#800
0#
#810
b110 ;
b11 <
1#
#820
0#
#830
b100 <
b111 ;
1#
#840
0#
#850
b1000 ;
b101 <
1#
#860
0#
#870
b0 <
1.
b1001 ;
1#
#880
0#
#890
b110000 !
b110000 *
b110000 K
b1000 "
b1000 2
b1000 I
b1010 ;
0.
b1 <
b11 J
1#
#900
0#
#910
b10 <
b0 ;
1%
1#
#920
0#
#930
b11001 !
b11001 *
b11001 K
b11001 '
b11001 :
b11001 G
b100 ,
b100 9
b100 C
0%
b1 ;
b11 <
b100 -
b100 >
b100 @
1#
#940
0#
#950
b100 <
b10 ;
1#
#960
0#
#970
b11 ;
b101 <
1#
#980
0#
#990
b0 <
1.
b100 ;
1#
#1000
0#
#1010
b1 !
b1 *
b1 K
b1 "
b1 2
b1 I
b101 ;
0.
b1 <
b0 J
1#
#1020
0#
#1030
b10 <
b110 ;
1#
#1040
0#
#1050
b111 ;
b11 <
1#
#1060
0#
#1070
b100 <
b1000 ;
1#
#1080
0#
#1090
b1001 ;
b101 <
1#
#1100
0#
#1110
b0 <
1.
b1010 ;
1#
#1120
0#
#1130
b10 "
b10 2
b10 I
b0 ;
1%
0.
b1 <
b1 J
1#
#1140
0#
#1150
b10010 '
b10010 :
b10010 G
b101 ,
b101 9
b101 C
b10 <
0%
b1 ;
b101 -
b101 >
b101 @
1#
#1160
0#
#1170
b10 ;
b11 <
1#
#1180
0#
#1190
b100 <
b11 ;
1#
#1200
0#
#1210
b100 ;
b101 <
1#
#1220
0#
#1230
b0 <
1.
b101 ;
1#
#1240
0#
#1250
b100 "
b100 2
b100 I
b110 ;
0.
b1 <
b10 J
1#
#1260
0#
#1270
b10 <
b111 ;
1#
#1280
0#
#1290
b1000 ;
b11 <
1#
#1300
0#
#1310
b100 <
b1001 ;
1#
#1320
0#
#1330
b1010 ;
b101 <
1#
#1340
0#
#1350
b0 <
1.
b0 ;
1%
1#
#1360
0#
#1370
b10 '
b10 :
b10 G
b10 !
b10 *
b10 K
b1000 "
b1000 2
b1000 I
b110 ,
b110 9
b110 C
0%
b1 ;
0.
b1 <
b11 J
b110 -
b110 >
b110 @
1#
#1380
0#
#1390
b10 <
b10 ;
1#
#1400
0#
#1410
b11 ;
b11 <
1#
#1420
0#
#1430
b100 <
b100 ;
1#
#1440
0#
#1450
b101 ;
b101 <
1#
#1460
0#
#1470
b0 <
1.
b110 ;
1#
#1480
0#
#1490
b1 !
b1 *
b1 K
b1 "
b1 2
b1 I
b111 ;
0.
b1 <
b0 J
1#
#1500
0#
#1510
b10 <
b1000 ;
1#
#1520
0#
#1530
b1001 ;
b11 <
1#
#1540
0#
#1550
b100 <
b1010 ;
1#
#1560
0#
#1570
b0 ;
1%
b101 <
1#
#1580
0#
#1590
b1111000 '
b1111000 :
b1111000 G
b111 ,
b111 9
b111 C
b0 <
1.
0%
b1 ;
b111 -
b111 >
b111 @
1#
#1600
0#
#1610
b10 "
b10 2
b10 I
b10 ;
0.
b1 <
b1 J
1#
#1620
0#
#1630
b10 <
b11 ;
1#
#1640
0#
#1650
b100 ;
b11 <
1#
#1660
0#
#1670
b100 <
b101 ;
1#
#1680
0#
#1690
b110 ;
b101 <
1#
#1700
0#
#1710
b0 <
1.
b111 ;
1#
#1720
0#
#1730
b100 "
b100 2
b100 I
b1000 ;
0.
b1 <
b10 J
1#
#1740
0#
#1750
b10 <
b1001 ;
1#
#1760
0#
#1770
b1010 ;
b11 <
1#
#1780
0#
#1790
b100 <
b0 ;
1%
1#
#1800
0#
#1810
b0 '
b0 :
b0 G
b1000 ,
b1000 9
b1000 C
0%
b1 ;
b101 <
b1000 -
b1000 >
b1000 @
1#
#1820
0#
#1830
b0 <
1.
b10 ;
1#
#1840
0#
#1850
b0 !
b0 *
b0 K
b1000 "
b1000 2
b1000 I
b11 ;
0.
b1 <
b11 J
1#
#1860
0#
#1870
b10 <
b100 ;
1#
#1880
0#
#1890
b101 ;
b11 <
1#
#1900
0#
#1910
b100 <
b110 ;
1#
#1920
0#
#1930
b111 ;
b101 <
1#
#1940
0#
#1950
b0 <
1.
b1000 ;
1#
#1960
0#
#1970
b1 !
b1 *
b1 K
b1 "
b1 2
b1 I
b1001 ;
0.
b1 <
b0 J
1#
#1980
0#
#1990
b10 <
b1010 ;
1#
#2000
0#
#2010
b0 ;
1%
b11 <
1#
#2020
0#
#2030
b10000 '
b10000 :
b10000 G
b1001 ,
b1001 9
b1001 C
b100 <
0%
b1 ;
b1001 -
b1001 >
b1001 @
1#
#2040
0#
#2050
b10 ;
b101 <
1#
#2060
0#
#2070
b0 <
1.
b11 ;
1#
#2080
0#
#2090
b10 "
b10 2
b10 I
b100 ;
0.
b1 <
b1 J
1#
#2100
0#
#2110
b10 <
b101 ;
1#
#2120
0#
#2130
b110 ;
b11 <
1#
#2140
0#
#2150
b100 <
b111 ;
1#
#2160
0#
#2170
b1000 ;
b101 <
1#
#2180
0#
#2190
b0 <
1.
b1001 ;
1#
#2200
0#
#2210
b100 "
b100 2
b100 I
b1010 ;
0.
b1 <
b10 J
1#
#2220
0#
#2230
b10 <
b0 ;
1%
1#
#2240
0#
#2250
b1111001 !
b1111001 *
b1111001 K
b1 '
b1 :
b1 G
b1111001 &
b1111001 8
b1111001 H
b0 ,
b0 9
b0 C
b1 +
b1 7
b1 D
0%
b1 ;
b11 <
b1010 -
b1010 >
b1010 @
1#
#2260
0#
#2270
b100 <
b10 ;
1#
#2280
0#
#2290
b11 ;
b101 <
1#
#2300
0#
#2310
b0 <
1.
b100 ;
1#
#2320
0#
#2330
b1 !
b1 *
b1 K
b1000 "
b1000 2
b1000 I
b101 ;
0.
b1 <
b11 J
1#
#2340
0#
#2350
b10 <
b110 ;
1#
#2360
0#
#2370
b111 ;
b11 <
1#
#2380
0#
#2390
b100 <
b1000 ;
1#
#2400
0#
#2410
b1001 ;
b101 <
1#
#2420
0#
#2430
b0 <
1.
b1010 ;
1#
#2440
0#
#2450
b1 "
b1 2
b1 I
b0 ;
1%
0.
b1 <
b0 J
1#
#2460
0#
#2470
b1111001 '
b1111001 :
b1111001 G
b1 ,
b1 9
b1 C
b10 <
0%
b1 ;
b1011 -
b1011 >
b1011 @
1#
#2480
0#
#2490
b10 ;
b11 <
1#
#2500
0#
#2510
b100 <
b11 ;
1#
#2520
0#
#2530
b100 ;
b101 <
1#
#2540
0#
#2550
b0 <
1.
b101 ;
1#
#2560
0#
#2570
b10 "
b10 2
b10 I
b110 ;
0.
b1 <
b1 J
1#
#2580
0#
#2590
b10 <
b111 ;
1#
#2600
0#
#2610
b1000 ;
b11 <
1#
#2620
0#
#2630
b100 <
b1001 ;
1#
#2640
0#
#2650
b1010 ;
b101 <
1#
#2660
0#
#2670
b0 <
1.
b0 ;
1%
1#
#2680
0#
#2690
b100100 '
b100100 :
b100100 G
b1111001 !
b1111001 *
b1111001 K
b100 "
b100 2
b100 I
b10 ,
b10 9
b10 C
0%
b1 ;
0.
b1 <
b10 J
b1100 -
b1100 >
b1100 @
1#
#2700
0#
#2710
b10 <
b10 ;
1#
#2720
0#
#2730
b11 ;
b11 <
1#
#2740
0#
#2750
b100 <
b100 ;
1#
#2760
0#
#2770
b101 ;
b101 <
1#
#2780
0#
#2790
b0 <
1.
b110 ;
1#
#2800
0#
#2810
b100100 !
b100100 *
b100100 K
b1000 "
b1000 2
b1000 I
b111 ;
0.
b1 <
b11 J
1#
#2820
0#
#2830
b10 <
b1000 ;
1#
#2840
0#
#2850
b1001 ;
b11 <
1#
#2860
0#
#2870
b100 <
b1010 ;
1#
#2880
0#
#2890
b0 ;
1%
b101 <
1#
#2900
0#
#2910
b110000 !
b110000 *
b110000 K
b110000 '
b110000 :
b110000 G
b11 ,
b11 9
b11 C
b0 <
1.
0%
b1 ;
b1101 -
b1101 >
b1101 @
1#
#2920
0#
#2930
b1 !
b1 *
b1 K
b1 "
b1 2
b1 I
b10 ;
0.
b1 <
b0 J
1#
#2940
0#
#2950
b10 <
b11 ;
1#
#2960
0#
#2970
b100 ;
b11 <
1#
#2980
0#
#2990
b100 <
b101 ;
1#
#3000
0#
#3010
b110 ;
b101 <
1#
#3020
0#
#3030
b0 <
1.
b111 ;
1#
#3040
0#
#3050
b10 "
b10 2
b10 I
b1000 ;
0.
b1 <
b1 J
1#
#3060
0#
#3070
b10 <
b1001 ;
1#
#3080
0#
#3090
b1010 ;
b11 <
1#
#3100
0#
#3110
b100 <
b0 ;
1%
1#
#3120
0#
#3130
b11001 '
b11001 :
b11001 G
b100 ,
b100 9
b100 C
0%
b1 ;
b101 <
b1110 -
b1110 >
b1110 @
1#
#3140
0#
#3150
b0 <
1.
b10 ;
1#
#3160
0#
#3170
b1111001 !
b1111001 *
b1111001 K
b100 "
b100 2
b100 I
b11 ;
0.
b1 <
b10 J
1#
#3180
0#
#3190
b10 <
b100 ;
1#
#3200
0#
#3210
b101 ;
b11 <
1#
#3220
0#
#3230
b100 <
b110 ;
1#
#3240
0#
#3250
b111 ;
b101 <
1#
#3260
0#
#3270
b0 <
1.
b1000 ;
1#
#3280
0#
#3290
b11001 !
b11001 *
b11001 K
b1000 "
b1000 2
b1000 I
b1001 ;
0.
b1 <
b11 J
1#
#3300
0#
#3310
b10 <
b1010 ;
1#
#3320
0#
#3330
b0 ;
1%
b11 <
1#
#3340
0#
#3350
b10010 !
b10010 *
b10010 K
b10010 '
b10010 :
b10010 G
b101 ,
b101 9
b101 C
b100 <
0%
b1 ;
b1111 -
b1111 >
b1111 @
1#
#3360
0#
#3370
b10 ;
b101 <
1#
#3380
0#
#3390
b0 <
1.
b11 ;
1#
#3400
0#
#3410
b1 !
b1 *
b1 K
b1 "
b1 2
b1 I
b100 ;
0.
b1 <
b0 J
1#
#3420
0#
#3430
b10 <
b101 ;
1#
#3440
0#
#3450
b110 ;
b11 <
1#
#3460
0#
#3470
b100 <
b111 ;
1#
#3480
0#
#3490
b1000 ;
b101 <
1#
#3500
0#
#3510
b0 <
1.
b1001 ;
1#
#3520
0#
#3530
b10 "
b10 2
b10 I
b1010 ;
0.
b1 <
b1 J
1#
#3540
0#
#3550
b10 <
b0 ;
1%
1#
#3560
0#
#3570
b10 '
b10 :
b10 G
b110 ,
b110 9
b110 C
0%
b1 ;
b11 <
b10000 -
b10000 >
b10000 @
1#
#3580
0#
#3590
b100 <
b10 ;
1#
#3600
0#
#3610
b11 ;
b101 <
1#
#3620
0#
#3630
b0 <
1.
b100 ;
1#
#3640
0#
#3650
b1111001 !
b1111001 *
b1111001 K
b100 "
b100 2
b100 I
b101 ;
0.
b1 <
b10 J
1#
#3660
0#
#3670
b10 <
b110 ;
1#
#3680
0#
#3690
b111 ;
b11 <
1#
#3700
0#
#3710
b100 <
b1000 ;
1#
#3720
0#
#3730
b1001 ;
b101 <
1#
#3740
0#
#3750
b0 <
1.
b1010 ;
1#
#3760
0#
#3770
b10 !
b10 *
b10 K
b1000 "
b1000 2
b1000 I
b0 ;
1%
0.
b1 <
b11 J
1#
#3780
0#
#3790
b1111000 !
b1111000 *
b1111000 K
b1111000 '
b1111000 :
b1111000 G
b111 ,
b111 9
b111 C
b10 <
0%
b1 ;
b10001 -
b10001 >
b10001 @
1#
#3800
0#
#3810
b10 ;
b11 <
1#
#3820
0#
#3830
b100 <
b11 ;
1#
#3840
0#
#3850
b100 ;
b101 <
1#
#3860
0#
#3870
b0 <
1.
b101 ;
1#
#3880
0#
#3890
b1 !
b1 *
b1 K
b1 "
b1 2
b1 I
b110 ;
0.
b1 <
b0 J
1#
#3900
0#
#3910
b10 <
b111 ;
1#
#3920
0#
#3930
b1000 ;
b11 <
1#
#3940
0#
#3950
b100 <
b1001 ;
1#
#3960
0#
#3970
b1010 ;
b101 <
1#
#3980
0#
#3990
b0 <
1.
b0 ;
1%
1#
#4000
0#
#4010
b0 '
b0 :
b0 G
b10 "
b10 2
b10 I
b1000 ,
b1000 9
b1000 C
0%
b1 ;
0.
b1 <
b1 J
b10010 -
b10010 >
b10010 @
1#
#4020
0#
#4030
b10 <
b10 ;
1#
#4040
0#
#4050
b11 ;
b11 <
1#
#4060
0#
#4070
b100 <
b100 ;
1#
#4080
0#
#4090
b101 ;
b101 <
1#
#4100
0#
#4110
b0 <
1.
b110 ;
1#
#4120
0#
#4130
b1111001 !
b1111001 *
b1111001 K
b100 "
b100 2
b100 I
b111 ;
0.
b1 <
b10 J
1#
#4140
0#
#4150
b10 <
b1000 ;
1#
#4160
0#
#4170
b1001 ;
b11 <
1#
#4180
0#
#4190
b100 <
b1010 ;
1#
#4200
0#
#4210
b0 ;
1%
b101 <
1#
#4220
0#
#4230
b10000 '
b10000 :
b10000 G
b1001 ,
b1001 9
b1001 C
b0 <
1.
0%
b1 ;
b10011 -
b10011 >
b10011 @
1#
#4240
0#
#4250
b10000 !
b10000 *
b10000 K
b1000 "
b1000 2
b1000 I
b10 ;
0.
b1 <
b11 J
1#
#4260
0#
#4270
b10 <
b11 ;
1#
#4280
0#
#4290
b100 ;
b11 <
1#
#4300
0#
#4310
b100 <
b101 ;
1#
#4320
0#
#4330
b110 ;
b101 <
1#
#4340
0#
#4350
b0 <
1.
b111 ;
1#
#4360
0#
#4370
b1 !
b1 *
b1 K
b1 "
b1 2
b1 I
b1000 ;
0.
b1 <
b0 J
1#
#4380
0#
#4390
b10 <
b1001 ;
1#
#4400
0#
#4410
b1010 ;
b11 <
1#
#4420
0#
#4430
b100 <
b0 ;
1%
1#
#4440
0#
#4450
b1 '
b1 :
b1 G
b100100 &
b100100 8
b100100 H
b0 ,
b0 9
b0 C
b10 +
b10 7
b10 D
0%
b1 ;
b101 <
b10100 -
b10100 >
b10100 @
1#
#4460
0#
#4470
b0 <
1.
b10 ;
1#
#4480
0#
#4490
b10 "
b10 2
b10 I
b11 ;
0.
b1 <
b1 J
1#
#4500
0#
#4510
b10 <
b100 ;
1#
#4520
0#
#4530
b101 ;
b11 <
1#
#4540
0#
#4550
b100 <
b110 ;
1#
#4560
0#
#4570
b111 ;
b101 <
1#
#4580
0#
#4590
b0 <
1.
b1000 ;
1#
#4600
0#
#4610
b100100 !
b100100 *
b100100 K
b100 "
b100 2
b100 I
b1001 ;
0.
b1 <
b10 J
1#
#4620
0#
#4630
b10 <
b1010 ;
1#
#4640
0#
#4650
b0 ;
1%
b11 <
1#
#4660
0#
#4670
b1111001 '
b1111001 :
b1111001 G
b1 ,
b1 9
b1 C
b100 <
0%
b1 ;
b10101 -
b10101 >
b10101 @
1#
#4680
0#
#4690
b10 ;
b101 <
1#
#4700
0#
#4710
b0 <
1.
b11 ;
1#
#4720
0#
#4730
b1111001 !
b1111001 *
b1111001 K
b1000 "
b1000 2
b1000 I
b100 ;
0.
b1 <
b11 J
1#
#4740
0#
#4750
b10 <
b101 ;
1#
#4760
0#
#4770
b110 ;
b11 <
1#
#4780
0#
#4790
b100 <
b111 ;
1#
#4800
0#
#4810
b1000 ;
b101 <
1#
#4820
0#
#4830
b0 <
1.
b1001 ;
1#
#4840
0#
#4850
b1 !
b1 *
b1 K
b1 "
b1 2
b1 I
b1010 ;
0.
b1 <
b0 J
1#
#4860
0#
#4870
b10 <
b0 ;
1%
1#
#4880
0#
#4890
b100100 '
b100100 :
b100100 G
b10 ,
b10 9
b10 C
0%
b1 ;
b11 <
b10110 -
b10110 >
b10110 @
1#
#4900
0#
#4910
b100 <
b10 ;
1#
#4920
0#
#4930
b11 ;
b101 <
1#
#4940
0#
#4950
b0 <
1.
b100 ;
1#
#4960
0#
#4970
b10 "
b10 2
b10 I
b101 ;
0.
b1 <
b1 J
1#
#4980
0#
#4990
b10 <
b110 ;
1#
#5000
0#
#5010
b111 ;
b11 <
1#
#5020
0#
#5030
b100 <
b1000 ;
1#
#5040
0#
#5050
b1001 ;
b101 <
1#
#5060
0#
#5070
b0 <
1.
b1010 ;
1#
#5080
0#
#5090
b100100 !
b100100 *
b100100 K
b100 "
b100 2
b100 I
b0 ;
1%
0.
b1 <
b10 J
1#
#5100
0#
#5110
b110000 '
b110000 :
b110000 G
b11 ,
b11 9
b11 C
b10 <
0%
b1 ;
b10111 -
b10111 >
b10111 @
1#
#5120
0#
#5130
b10 ;
b11 <
1#
#5140
0#
#5150
b100 <
b11 ;
1#
#5160
0#
#5170
b100 ;
b101 <
1#
#5180
0#
#5190
b0 <
1.
b101 ;
1#
#5200
0#
#5210
b110000 !
b110000 *
b110000 K
b1000 "
b1000 2
b1000 I
b110 ;
0.
b1 <
b11 J
1#
#5220
0#
#5230
b10 <
b111 ;
1#
#5240
0#
#5250
b1000 ;
b11 <
1#
#5260
0#
#5270
b100 <
b1001 ;
1#
#5280
0#
#5290
b1010 ;
b101 <
1#
#5300
0#
#5310
b0 <
1.
b0 ;
1%
1#
#5320
0#
#5330
b11001 '
b11001 :
b11001 G
b1 !
b1 *
b1 K
b1 "
b1 2
b1 I
b100 ,
b100 9
b100 C
0%
b1 ;
0.
b1 <
b0 J
b11000 -
b11000 >
b11000 @
1#
#5340
0#
#5350
b10 <
b10 ;
1#
#5360
0#
#5370
b11 ;
b11 <
1#
#5380
0#
#5390
b100 <
b100 ;
1#
#5400
0#
#5410
b101 ;
b101 <
1#
#5420
0#
#5430
b0 <
1.
b110 ;
1#
#5440
0#
#5450
b10 "
b10 2
b10 I
b111 ;
0.
b1 <
b1 J
1#
#5460
0#
#5470
b10 <
b1000 ;
1#
#5480
0#
#5490
b1001 ;
b11 <
1#
#5500
0#
#5510
b100 <
b1010 ;
1#
#5520
0#
#5530
b0 ;
1%
b101 <
1#
#5540
0#
#5550
b10010 '
b10010 :
b10010 G
b101 ,
b101 9
b101 C
b0 <
1.
0%
b1 ;
b11001 -
b11001 >
b11001 @
1#
#5560
0#
#5570
b100100 !
b100100 *
b100100 K
b100 "
b100 2
b100 I
b10 ;
0.
b1 <
b10 J
1#
#5580
0#
#5590
b10 <
b11 ;
1#
#5600
0#
#5610
b100 ;
b11 <
1#
#5620
0#
#5630
b100 <
b101 ;
1#
#5640
0#
#5650
b110 ;
b101 <
1#
#5660
0#
#5670
b0 <
1.
b111 ;
1#
#5680
0#
#5690
b10010 !
b10010 *
b10010 K
b1000 "
b1000 2
b1000 I
b1000 ;
0.
b1 <
b11 J
1#
#5700
0#
#5710
b10 <
b1001 ;
1#
#5720
0#
#5730
b1010 ;
b11 <
1#
#5740
0#
#5750
b100 <
b0 ;
1%
1#
#5760
0#
#5770
b10 !
b10 *
b10 K
b10 '
b10 :
b10 G
b110 ,
b110 9
b110 C
0%
b1 ;
b101 <
b11010 -
b11010 >
b11010 @
1#
#5780
0#
#5790
b0 <
1.
b10 ;
1#
#5800
0#
#5810
b1 !
b1 *
b1 K
b1 "
b1 2
b1 I
b11 ;
0.
b1 <
b0 J
1#
#5820
0#
#5830
b10 <
b100 ;
1#
#5840
0#
#5850
b101 ;
b11 <
1#
#5860
0#
#5870
b100 <
b110 ;
1#
#5880
0#
#5890
b111 ;
b101 <
1#
#5900
0#
#5910
b0 <
1.
b1000 ;
1#
#5920
0#
#5930
b10 "
b10 2
b10 I
b1001 ;
0.
b1 <
b1 J
1#
#5940
0#
#5950
b10 <
b1010 ;
1#
#5960
0#
#5970
b0 ;
1%
b11 <
1#
#5980
0#
#5990
b1111000 '
b1111000 :
b1111000 G
b111 ,
b111 9
b111 C
b100 <
0%
b1 ;
b11011 -
b11011 >
b11011 @
1#
#6000
0#
#6010
b10 ;
b101 <
1#
#6020
0#
#6030
b0 <
1.
b11 ;
1#
#6040
0#
