apb/apb.v
module apb_master (
    input pclk,
    input reset,
    input start,
    input rw,              
    input [7:0] add,
    input [7:0] write_data,
    input [7:0] prdata,
    input pready,

    output reg psel,
    output reg pena,
    output reg [7:0] padd,
    output reg [7:0] pwdata,
    output reg pwrite,
    output reg [7:0] read_data
);

    parameter IDLE   = 2'b00;
    parameter SETUP  = 2'b01;
    parameter ACCESS = 2'b10;

    reg [1:0] state, next_state;


    // State register
    always @(posedge pclk or negedge reset) begin
        if (!reset)
            state <= IDLE;
        else
            state <= next_state;
    end


    // Next state logic
    always @(*) begin
        case (state)

            IDLE: begin
                if (start)
                    next_state = SETUP;
                else
                    next_state = IDLE;
            end

            SETUP: begin
                next_state = ACCESS;
            end

            ACCESS: begin
                if (pready)
                    next_state = IDLE;
                else
                    next_state = ACCESS;
            end

            default:
                next_state = IDLE;

        endcase
    end

    always @(*) begin
        psel   = 1'b0;
        pena   = 1'b0;
        padd   = add;
        pwdata = write_data;
        pwrite = rw;

        case (state)

            IDLE: begin
                psel = 1'b0;
                pena = 1'b0;
            end

            SETUP: begin
                psel = 1'b1;
                pena = 1'b0;
            end

            ACCESS: begin
                psel = 1'b1;
                pena = 1'b1;
            end
        endcase
    end
    always @(posedge pclk or negedge reset) begin
        if (!reset) begin
            read_data <= 8'h00;
        end
        else begin
            if (state == ACCESS &&
                !pwrite &&
                pready) begin
                read_data <= prdata;
            end
        end
end
endmodule

module apb_slave (
    input pclk,
    input reset,
    input psel,
    input pena,
    input pwrite,
    input [7:0] padd,
    input [7:0] pwdata,
    output reg [7:0] prdata,
    output  pready
);
    assign pready = 1'b1;
    reg [7:0] mem [0:255];
    integer i;
 
       always @(posedge pclk or negedge reset) begin
        if (!reset) begin
            for (i = 0; i < 256; i = i + 1)
                mem[i] <= 8'h00;
        end
        else begin
            if (psel && pena && pwrite ) begin
    		    mem[padd] <= pwdata;
		end
            end
        end
    
    always @(*) begin
        if (psel && pena && !pwrite ) 
            prdata = mem[padd];
        else
		prdata <= 8'h00;
      end

endmodule

apb/topmodule.v
module apb_top (
    input        pclk,
    input        reset,
    input        start,
    input        rw,
    input  [7:0] add,
    input  [7:0] write_data,
    output [7:0] read_data
);
    wire        psel;
    wire        pena;
    wire [7:0]  padd;
    wire [7:0]  pwdata;
    wire        pwrite;
    wire [7:0]  prdata;
    wire        pready;
    apb_master master (
        .pclk (pclk),
        .reset (reset),
        .start (start),
        .rw (rw),
        .add (add),
        .write_data (write_data),
        .prdata (prdata),
        .pready (pready),
        .psel (psel),
        .pena (pena),
        .padd (padd),
        .pwdata (pwdata),
        .pwrite (pwrite),
        .read_data(read_data)
    );
    apb_slave slave (
        .pclk (pclk),
        .reset (reset),
        .psel (psel),
        .pena (pena),
        .pwrite (pwrite),
        .padd (padd),
        .pwdata (pwdata),
        .prdata (prdata),
        .pready (pready)
    );
endmodule

apb/apb_tb.v
module apb_tb;
    reg pclk;
    reg reset;
    reg start;
    reg rw;
    reg [7:0] add;
    reg [7:0] write_data;
    wire [7:0] read_data;
    apb_top uut (
        .pclk (pclk),
        .reset (reset),
        .start (start),
        .rw (rw),
        .add (add),
        .write_data (write_data),
        .read_data (read_data)
    );
    always #5 pclk = ~pclk;
    initial begin
        pclk = 0;
        reset = 0;
        start = 0;
        rw = 0;
        add = 8'h00;
        write_data = 8'h00;

	#10;
        reset = 1;
        #10;
        add = 8'h10;
        write_data = 8'hAA;
        rw = 1;          
        start = 1;
        #10;
        start = 0;
        #40;


	add = 8'h10;
        rw = 0;          
        start = 1;
        #10;
        start = 0;
        #30;
        $display("READ DATA = %h", read_data);
        #20;
        $finish;
    end
    initial begin
        $dumpfile("apb.vcd");
        $dumpvars(0, apb_tb);
    end
    initial begin
        $monitor("TIME=%0t PSEL=%b PENA=%b PWRITE=%b PADDR=%h PWDATA=%h  READ_DATA=%h",
            $time,
            uut.psel,
            uut.pena,
            uut.pwrite,
            uut.padd,
            uut.pwdata,
            read_data);
        
    end
endmodule

apb/apb.vcd
$date
	Mon Sep  7 06:47:22 2026
$end
$version
	Icarus Verilog
$end
$timescale
	1s
$end
$scope module apb_tb $end
$var wire 8 ! read_data [7:0] $end
$var reg 8 " add [7:0] $end
$var reg 1 # pclk $end
$var reg 1 $ reset $end
$var reg 1 % rw $end
$var reg 1 & start $end
$var reg 8 ' write_data [7:0] $end
$scope module uut $end
$var wire 8 ( add [7:0] $end
$var wire 1 # pclk $end
$var wire 1 ) pready $end
$var wire 1 $ reset $end
$var wire 1 % rw $end
$var wire 1 & start $end
$var wire 8 * write_data [7:0] $end
$var wire 8 + read_data [7:0] $end
$var wire 1 , pwrite $end
$var wire 8 - pwdata [7:0] $end
$var wire 1 . psel $end
$var wire 8 / prdata [7:0] $end
$var wire 1 0 pena $end
$var wire 8 1 padd [7:0] $end
$scope module master $end
$var wire 8 2 add [7:0] $end
$var wire 1 # pclk $end
$var wire 1 ) pready $end
$var wire 1 $ reset $end
$var wire 1 % rw $end
$var wire 1 & start $end
$var wire 8 3 write_data [7:0] $end
$var wire 8 4 prdata [7:0] $end
$var parameter 2 5 ACCESS $end
$var parameter 2 6 IDLE $end
$var parameter 2 7 SETUP $end
$var reg 2 8 next_state [1:0] $end
$var reg 8 9 padd [7:0] $end
$var reg 1 0 pena $end
$var reg 1 . psel $end
$var reg 8 : pwdata [7:0] $end
$var reg 1 , pwrite $end
$var reg 8 ; read_data [7:0] $end
$var reg 2 < state [1:0] $end
$upscope $end
$scope module slave $end
$var wire 8 = padd [7:0] $end
$var wire 1 # pclk $end
$var wire 1 0 pena $end
$var wire 1 ) pready $end
$var wire 1 . psel $end
$var wire 8 > pwdata [7:0] $end
$var wire 1 , pwrite $end
$var wire 1 $ reset $end
$var reg 8 ? prdata [7:0] $end
$var integer 32 @ i [31:0] $end
$upscope $end
$upscope $end
$upscope $end
$enddefinitions $end
$comment Show the parameter values. $end
$dumpall
b1 7
b0 6
b10 5
$end
#0
$dumpvars
b100000000 @
b0 ?
b0 >
b0 =
b0 <
b0 ;
b0 :
b0 9
b0 8
b0 4
b0 3
b0 2
b0 1
00
b0 /
0.
b0 -
0,
b0 +
b0 *
1)
b0 (
b0 '
0&
0%
0$
0#
b0 "
b0 !
$end
#5
b100000000 @
1#
#10
0#
1$
#15
1#
#20
b1 8
1,
b10101010 -
b10101010 :
b10101010 >
b10000 1
b10000 9
b10000 =
0#
1&
1%
b10101010 '
b10101010 *
b10101010 3
b10000 "
b10000 (
b10000 2
#25
1.
b10 8
b1 <
1#
#30
0#
0&
#35
10
1.
b0 8
b10 <
1#
#40
0#
#45
00
0.
b0 <
1#
#50
0#
#55
1#
#60
0#
#65
1#
#70
b1 8
0,
0#
1&
0%
#75
1.
b10 8
b1 <
1#
#80
0#
0&
#85
b10101010 /
b10101010 4
b10101010 ?
10
1.
b0 8
b10 <
1#
#90
0#
#95
b0 /
b0 4
b0 ?
00
0.
b0 <
b10101010 !
b10101010 +
b10101010 ;
1#
