fifo/fifo.v
/* module fifo(
input clk,
input rst,
input wr_ena,
input rd_ena,
output full,
output empty,
input [7:0]data_in,
output reg [7:0]data_out);
reg[7:0]mem[7:0];
reg [2:0]wr_pr;
reg [2:0]rd_pr;
reg [3:0]count;
always@(posedge clk or negedge rst)begin
	if(!rst)begin
wr_pr<=3'd0;
rd_pr<=3'd0;
data_out<=8'd0;
count<=4'd0;
end
else begin

	if(wr_ena && !full)begin
mem[wr_pr] <= data_in;
wr_pr <= wr_pr+3'd1;
end

if(rd_ena && !empty)begin
	data_out<=mem[rd_pr];
rd_pr<=rd_pr+3'd1;
end

if((wr_ena && !full) && !(rd_ena && !empty))begin
count<=count+4'd1;
end

else
	if((rd_ena && !empty) && !(wr_ena && !full))begin
count<=count-4'd1;
end

else if((wr_ena && !full)&&(rd_ena && !empty))begin
count<=count;
end

else begin
	count<=count;
end
end
end
assign full=(count==8);
assign empty=(count==0);
endmodule */ 


module fifo_sync (input clk,
	 input cs,
	 input rst_n,
	 input wr_en,
	 input rd_en,
	 input [7:0]data_in,
	 output reg[7:0]data_out,
	 output full,
	 output empty);
 reg [3:0]wr_p;
 reg [3:0]rd_p;
 reg [7:0]mem[7:0];
 always@(posedge clk or negedge rst_n)begin
	 if(!rst_n)begin
		 wr_p<=4'b0000;
	 end
	 else if(cs && wr_en && !full)begin
		 mem[wr_p[2:0]]<=data_in;
		 wr_p<=wr_p + 1'b1;
	 end
 end
 always@(posedge clk or negedge rst_n)begin
	 if(!rst_n)begin
		 rd_p<=4'b0000;
		data_out<=8'b00000000;
	end

	 else if(cs && rd_en && !empty)begin
			 data_out<=mem[rd_p[2:0]];
			 rd_p<=rd_p + 1'b1;
	 end
 end
	
	 assign empty=(wr_p == rd_p);
          assign full = (wr_p[2:0] == rd_p[2:0]) && (wr_p[3] != rd_p[3]);
	  endmodule

fifo/fifo_tb.v
/* module fifo_tb;
reg clk;
reg rst;
reg wr_ena;
reg rd_ena;
reg [7:0] data_in;
wire full;
wire empty;
wire [7:0] data_out;
fifo uut (
    .clk(clk),
    .rst(rst),
    .wr_ena(wr_ena),
    .rd_ena(rd_ena),
    .full(full),
    .empty(empty),
    .data_in(data_in),
    .data_out(data_out)
);
always #5 clk = ~clk;
initial begin
    clk     = 0;
    rst     = 0;
    wr_ena  = 0;
    rd_ena  = 0;
    data_in = 8'd0;
    #10;
    rst = 1;
    wr_ena = 1;
    data_in = 8'd10; #10;
    data_in = 8'd20; #10;
    data_in = 8'd30; #10;
    data_in = 8'd40; #10;
    data_in = 8'd50; #10;
    data_in = 8'd60; #10;
    data_in = 8'd70; #10;
    data_in = 8'd80; #10;
    wr_ena = 0;
    #10;
    rd_ena = 1;
    #10;   
    #10;   
    #10;   
    #10;   
    #10;   
    #10;   
    #10;   
    #10;   
    rd_ena = 0;
    #10;
    $finish;
end
initial begin
    $monitor(
        "TIME=%0t  CLK=%b  RST=%b  WR=%b  RD=%b  DATA_IN=%d  DATA_OUT=%d  FULL=%b  EMPTY=%b",
        $time,
        clk,
        rst,
        wr_ena,
        rd_ena,
        data_in,
        data_out,
        full,
        empty
    );
end
endmodule */


`timescale 1ns/1ps

module fifo_sync_tb;
    reg clk;
    reg cs;
    reg rst_n;
    reg wr_en;
    reg rd_en;
    reg [7:0] data_in;
    wire [7:0] data_out;
    wire full;
    wire empty;

    fifo_sync uut (
        .clk(clk),
        .cs(cs),
        .rst_n(rst_n),
        .wr_en(wr_en),
        .rd_en(rd_en),
        .data_in(data_in),
        .data_out(data_out),
        .full(full),
        .empty(empty)
    );

    always #5 clk = ~clk;

    initial begin
        $monitor("TIME=%0t | CLK=%b | CS=%b | WR_EN=%b | RD_EN=%b | DATA_IN=%h | DATA_OUT=%h | WR_P=%b | RD_P=%b | FULL=%b | EMPTY=%b",
                  $time, clk, cs, wr_en, rd_en,
                  data_in, data_out,
                  uut.wr_p, uut.rd_p,
                  full, empty);
    end
    initial begin

        clk     = 0;
        cs      = 0;
        rst_n   = 0;
        wr_en   = 0;
        rd_en   = 0;
        data_in = 8'h00;
        #10;

        rst_n = 1;
        cs    = 1;
        #10;

        wr_en   = 1;
        data_in = 8'hC1;
        #10;
        data_in = 8'h35;
        #10;
        data_in = 8'h40;
        #10;
        data_in = 8'h50;
        #10;
        data_in = 8'h13;
        #10;
        data_in = 8'hA5;
        #10;
        data_in = 8'h6B;
        #10;
        data_in = 8'hF3;
        #10;
        wr_en = 0;
        #10;
        rd_en = 1;
        #80;
        rd_en = 0;
        #20;
        $finish;
    end
    initial begin
        $dumpfile("fifo_sync.vcd");
        $dumpvars(0, fifo_sync_tb);
    end

endmodule

fifo/fifo_sync.vcd
$date
	Wed Sep  2 08:45:33 2026
$end
$version
	Icarus Verilog
$end
$timescale
	1ps
$end
$scope module fifo_sync_tb $end
$var wire 1 ! full $end
$var wire 1 " empty $end
$var wire 8 # data_out [7:0] $end
$var reg 1 $ clk $end
$var reg 1 % cs $end
$var reg 8 & data_in [7:0] $end
$var reg 1 ' rd_en $end
$var reg 1 ( rst_n $end
$var reg 1 ) wr_en $end
$scope module uut $end
$var wire 1 $ clk $end
$var wire 1 % cs $end
$var wire 8 * data_in [7:0] $end
$var wire 1 ! full $end
$var wire 1 ' rd_en $end
$var wire 1 ( rst_n $end
$var wire 1 ) wr_en $end
$var wire 1 " empty $end
$var reg 8 + data_out [7:0] $end
$var reg 4 , rd_p [3:0] $end
$var reg 4 - wr_p [3:0] $end
$upscope $end
$upscope $end
$enddefinitions $end
$comment Show the parameter values. $end
$dumpall
$end
#0
$dumpvars
b0 -
b0 ,
b0 +
b0 *
0)
0(
0'
b0 &
0%
0$
b0 #
1"
0!
$end
#5000
1$
#10000
0$
1%
1(
#15000
1$
#20000
0$
b11000001 &
b11000001 *
1)
#25000
0"
b1 -
1$
#30000
0$
b110101 &
b110101 *
#35000
b10 -
1$
#40000
0$
b1000000 &
b1000000 *
#45000
b11 -
1$
#50000
0$
b1010000 &
b1010000 *
#55000
b100 -
1$
#60000
0$
b10011 &
b10011 *
#65000
b101 -
1$
#70000
0$
b10100101 &
b10100101 *
#75000
b110 -
1$
#80000
0$
b1101011 &
b1101011 *
#85000
b111 -
1$
#90000
0$
b11110011 &
b11110011 *
#95000
1!
b1000 -
1$
#100000
0$
0)
#105000
1$
#110000
0$
1'
#115000
0!
b1 ,
b11000001 #
b11000001 +
1$
#120000
0$
#125000
b10 ,
b110101 #
b110101 +
1$
#130000
0$
#135000
b11 ,
b1000000 #
b1000000 +
1$
#140000
0$
#145000
b100 ,
b1010000 #
b1010000 +
1$
#150000
0$
#155000
b101 ,
b10011 #
b10011 +
1$
#160000
0$
#165000
b110 ,
b10100101 #
b10100101 +
1$
#170000
0$
#175000
b111 ,
b1101011 #
b1101011 +
1$
#180000
0$
#185000
1"
b1000 ,
b11110011 #
b11110011 +
1$
#190000
0$
0'
