mode1/mode1.v
module spi_protocol (
    input  wire       clk,
    input  wire       reset,
    input  wire       start,
    input  wire [7:0] tx_data,
    input  wire       miso,

    output reg        sclk,
    output reg        mosi,
    output reg        cs_n,
    output reg [7:0]  rx_data,
    output reg        busy,
    output reg        done
);

    localparam ST_IDLE     = 2'd0;
    localparam ST_ASSERT   = 2'd1;
    localparam ST_TRANSFER = 2'd2;
    localparam ST_DONE     = 2'd3;

    reg [1:0] state;
    reg [7:0] tx_shift;
    reg [7:0] rx_shift;
    reg [2:0] bit_cnt;

    always @(posedge clk) begin

        if (reset) begin

            state    <= ST_IDLE;
            sclk     <= 1'b0;
            mosi     <= 1'b0;
            cs_n     <= 1'b1;
            rx_data  <= 8'h00;
            busy     <= 1'b0;
            done     <= 1'b0;

            tx_shift <= 8'h00;
            rx_shift <= 8'h00;
            bit_cnt  <= 3'd7;
        end

        else begin

            done <= 1'b0;

            case (state)

                // ==================================
                // IDLE
                // ==================================
                ST_IDLE: begin

                    cs_n <= 1'b1;
                    busy <= 1'b0;
                    sclk <= 1'b0;

                    if (start) begin

                        tx_shift <= tx_data;
                        rx_shift <= 8'h00;
                        bit_cnt  <= 3'd7;

                        cs_n <= 1'b0;
                        busy <= 1'b1;

                        state <= ST_ASSERT;
                    end
                end


                // ==================================
                // ASSERT
                // ==================================
                ST_ASSERT: begin

                    // SPI MODE 1
                    // CPOL = 0
                    // CPHA = 1
                    //
                    // SCLK idle = LOW
                    // Rising edge  = LAUNCH
                    // Falling edge = SAMPLE

                    sclk <= 1'b0;
                    cs_n <= 1'b0;

                    // First data bit
                    mosi <= tx_shift[7];

                    state <= ST_TRANSFER;
                end


                // ==================================
                // TRANSFER
                // ==================================
                ST_TRANSFER: begin

                    // --------------------------------
                    // Rising Edge
                    // MODE 1 -> LAUNCH DATA
                    // --------------------------------
                    if (sclk == 1'b0) begin

                        sclk <= 1'b1;

                    end


                    // --------------------------------
                    // Falling Edge
                    // MODE 1 -> SAMPLE DATA
                    // --------------------------------
                    else begin

                        sclk <= 1'b0;

                        // Sample MISO
                        rx_shift <= {
                            rx_shift[6:0],
                            miso
                        };

                        // Check final bit
                        if (bit_cnt == 3'd0) begin

                            state <= ST_DONE;

                        end

                        else begin

                            bit_cnt <= bit_cnt - 3'd1;

                            // Shift TX data
                            tx_shift <= {
                                tx_shift[6:0],
                                1'b0
                            };

                            // Send next bit
                            mosi <= tx_shift[6];
                        end
                    end
                end


                // ==================================
                // DONE
                // ==================================
                ST_DONE: begin

                    cs_n <= 1'b1;
                    busy <= 1'b0;

                    sclk <= 1'b0;
                    mosi <= 1'b0;

                    // Store received data
                    rx_data <= rx_shift;

                    done <= 1'b1;

                    state <= ST_IDLE;
                end


                // ==================================
                // DEFAULT
                // ==================================
                default: begin

                    state <= ST_IDLE;
                    cs_n  <= 1'b1;
                    busy  <= 1'b0;
                    sclk  <= 1'b0;
                    mosi  <= 1'b0;

                end

            endcase
        end
    end

endmodule

mode1/mode1_tb.v
`timescale 1ns/1ps

module spi_protocol_tb;

    reg        clk;
    reg        reset;
    reg        start;
    reg [7:0]  tx_data;
    reg        miso;

    wire       sclk;
    wire       mosi;
    wire       cs_n;
    wire [7:0] rx_data;
    wire       busy;
    wire       done;

    // DUT
    spi_protocol dut (
        .clk      (clk),
        .reset    (reset),
        .start    (start),
        .tx_data  (tx_data),
        .miso     (miso),
        .sclk     (sclk),
        .mosi     (mosi),
        .cs_n     (cs_n),
        .rx_data  (rx_data),
        .busy     (busy),
        .done     (done)
    );

    // System clock
    always #5 clk = ~clk;


    // Slave data
    reg [7:0] slave_data;
    integer i;


    initial begin

        // Initial values
        clk       = 1'b0;
        reset     = 1'b1;
        start     = 1'b0;
        tx_data   = 8'h00;
        miso      = 1'b0;

        slave_data = 8'hA5;


        // Reset
        #20;
        reset = 1'b0;

        // Master transmit data
        tx_data = 8'hA5;

        // Start SPI transfer
        #10;
        start = 1'b1;

        #10;
        start = 1'b0;


        // ----------------------------------------
        // SPI Slave
        // Mode 1:
        // Rising edge  -> Master launches MOSI
        // Falling edge -> Slave launches MISO
        // ----------------------------------------

        wait(cs_n == 1'b0);

        // Send first MISO bit
        miso = slave_data[7];

        for (i = 7; i >= 0; i = i - 1) begin

            // Wait for rising edge
            @(posedge sclk);

            // Mode 1:
            // MISO changes on falling edge
            @(negedge sclk);

            if (i > 0)
                miso = slave_data[i-1];
        end


        // Wait until transfer is complete
        wait(done == 1'b1);

        #20;

        $display("--------------------------------");
        $display("SPI MODE 1 TRANSFER COMPLETE");
        $display("Master TX Data = %h", tx_data);
        $display("Slave  TX Data = %h", slave_data);
        $display("Master RX Data = %h", rx_data);
        $display("--------------------------------");

        #20;
        $finish;

    end


    // Generate waveform
    initial begin

        $dumpfile("spi_protocol.vcd");
        $dumpvars(0, spi_protocol_tb);

    end

endmodule

mode1/spi_protocol.vcd
$date
	Wed Aug 19 18:00:56 2026
$end
$version
	Icarus Verilog
$end
$timescale
	1ps
$end
$scope module spi_protocol_tb $end
$var wire 1 ! sclk $end
$var wire 8 " rx_data [7:0] $end
$var wire 1 # mosi $end
$var wire 1 $ done $end
$var wire 1 % cs_n $end
$var wire 1 & busy $end
$var reg 1 ' clk $end
$var reg 1 ( miso $end
$var reg 1 ) reset $end
$var reg 8 * slave_data [7:0] $end
$var reg 1 + start $end
$var reg 8 , tx_data [7:0] $end
$var integer 32 - i [31:0] $end
$scope module dut $end
$var wire 1 ' clk $end
$var wire 1 ( miso $end
$var wire 1 ) reset $end
$var wire 1 + start $end
$var wire 8 . tx_data [7:0] $end
$var parameter 2 / ST_ASSERT $end
$var parameter 2 0 ST_DONE $end
$var parameter 2 1 ST_IDLE $end
$var parameter 2 2 ST_TRANSFER $end
$var reg 3 3 bit_cnt [2:0] $end
$var reg 1 & busy $end
$var reg 1 % cs_n $end
$var reg 1 $ done $end
$var reg 1 # mosi $end
$var reg 8 4 rx_data [7:0] $end
$var reg 8 5 rx_shift [7:0] $end
$var reg 1 ! sclk $end
$var reg 2 6 state [1:0] $end
$var reg 8 7 tx_shift [7:0] $end
$upscope $end
$upscope $end
$enddefinitions $end
$comment Show the parameter values. $end
$dumpall
b10 2
b0 1
b11 0
b1 /
$end
#0
$dumpvars
bx 7
bx 6
bx 5
bx 4
bx 3
b0 .
bx -
b0 ,
0+
b10100101 *
1)
0(
0'
x&
x%
x$
x#
bx "
x!
$end
#5000
b111 3
b0 5
b0 7
0$
0&
b0 "
b0 4
1%
0#
0!
b0 6
1'
#10000
0'
#15000
1'
#20000
0'
b10100101 ,
b10100101 .
0)
#25000
1'
#30000
0'
1+
#35000
b1 6
1&
0%
b10100101 7
1'
#40000
0'
b111 -
1(
0+
#45000
b10 6
1#
1'
#50000
0'
#55000
1!
1'
#60000
0'
#65000
b110 -
0(
0#
b1001010 7
b110 3
b1 5
0!
1'
#70000
0'
#75000
1!
1'
#80000
0'
#85000
b101 -
1(
1#
b10010100 7
b101 3
b10 5
0!
1'
#90000
0'
#95000
1!
1'
#100000
0'
#105000
b100 -
0(
0#
b101000 7
b100 3
b101 5
0!
1'
#110000
0'
#115000
1!
1'
#120000
0'
#125000
b11 -
b1010000 7
b11 3
b1010 5
0!
1'
#130000
0'
#135000
1!
1'
#140000
0'
#145000
b10 -
1(
1#
b10100000 7
b10 3
b10100 5
0!
1'
#150000
0'
#155000
1!
1'
#160000
0'
#165000
b1 -
0(
0#
b1000000 7
b1 3
b101001 5
0!
1'
#170000
0'
#175000
1!
1'
#180000
0'
#185000
b0 -
1(
1#
b10000000 7
b0 3
b1010010 5
0!
1'
#190000
0'
#195000
1!
1'
#200000
0'
#205000
b11111111111111111111111111111111 -
b11 6
b10100101 5
0!
1'
#210000
0'
#215000
b0 6
1$
b10100101 "
b10100101 4
0#
0&
1%
1'
#220000
0'
#225000
0$
1'
