spi_protocol/spi_protocol.v
module spi_protocol (
    input  wire       clk,
    input  wire       reset,
    input  wire       start,
    input  wire [7:0] tx_data,
    input  wire       miso,
    output reg        sclk,
    output reg        mosi,
    output reg        cs_n,
    output reg [7:0]  rx_data,
    output reg        busy,
    output reg        done
);
    localparam ST_IDLE     = 2'd0;
    localparam ST_ASSERT   = 2'd1;
    localparam ST_TRANSFER = 2'd2;
    localparam ST_DONE     = 2'd3;
    reg [1:0] state;
    reg [7:0] tx_shift;
    reg [7:0] rx_shift;
    reg [2:0] bit_cnt;
    always @(posedge clk) begin
        if (reset) begin
            state    <= ST_IDLE;
            sclk     <= 1'b0;
            mosi     <= 1'b0;
            cs_n     <= 1'b1;
            rx_data  <= 8'h00;
            busy     <= 1'b0;
            done     <= 1'b0;
            tx_shift <= 8'h00;
            rx_shift <= 8'h00;
            bit_cnt  <= 3'd7;
        end
        else begin
            done <= 1'b0;
            case (state)
                ST_IDLE: begin
                    cs_n <= 1'b1;
                    busy <= 1'b0;
                    sclk <= 1'b0;
                    if (start) begin
                        tx_shift <= tx_data;
                        rx_shift <= 8'h00;
                        bit_cnt <= 3'd7;
                        mosi <= tx_data[7];
                        cs_n <= 1'b0;
                        busy <= 1'b1;
                        state <= ST_ASSERT;
                    end
                end
                ST_ASSERT: begin
                    // SPI MODE 0
                    // CPOL = 0
                    // CPHA = 0
                    // SCLK idle = LOW
                    // Rising edge  = SAMPLE
                    // Falling edge = LAUNCH

                    sclk <= 1'b0;
                    cs_n <= 1'b0;
                    mosi <= tx_shift[7];
                    state <= ST_TRANSFER;
                end
                ST_TRANSFER: begin
                    if (sclk == 1'b0) begin
                        sclk <= 1'b1;
                        // Sample MISO
                        rx_shift <= {
                            rx_shift[6:0],
                            miso
                        };
                    end
                    // Falling Edge
                    // MODE 0 -> LAUNCH
                    else begin
                        sclk <= 1'b0;
                        // Shift TX data
                        tx_shift <= {
                            tx_shift[6:0],
                            1'b0
                        };
                        // Send next bit
                        if (bit_cnt != 3'd0) begin
                            mosi <= tx_shift[6];
                        end
                    end
                    // Check for final bit
                    if ((sclk == 1'b0) &&
                        (bit_cnt == 3'd0)) begin

                        // Transfer complete
                        state <= ST_DONE;

                        // Deselect slave
                        cs_n <= 1'b1;

                        // Communication finished
                        busy <= 1'b0;

                        // Store final received data
                        rx_data <= {
                            rx_shift[6:0],
                            miso
                        };

                        // Transfer complete pulse
                        done <= 1'b1;

                        // Return SCLK to idle
                        sclk <= 1'b0;

                        mosi <= 1'b0;
                    end

                    else if (sclk == 1'b0) begin

                        // One bit sampled
                        bit_cnt <= bit_cnt - 3'd1;

                    end
                end
                ST_DONE: begin
                    cs_n <= 1'b1;
                    busy <= 1'b0;
                    // Mode 0 idle level
                    sclk <= 1'b0;
                    mosi <= 1'b0;
                    state <= ST_IDLE;
                end
                default: begin
                    state <= ST_IDLE;
                    cs_n <= 1'b1;
                    busy <= 1'b0;
                    sclk <= 1'b0;
                    mosi <= 1'b0;
                end
            endcase
        end
    end
endmodule

spi_protocol/spi_protocol_tb.v
module spi_protocol_tb;
    reg        clk;
    reg        reset;
    reg        start;
    reg [7:0]  tx_data;
    reg        miso;

    wire       sclk;
    wire       mosi;
    wire       cs_n;
    wire [7:0] rx_data;
    wire       busy;
    wire       done;
    // Slave data
    reg [7:0] slave_tx_data;
    integer i;
    spi_protocol uut (
        .clk     (clk),
        .reset   (reset),
        .start   (start),
        .tx_data (tx_data),
        .miso    (miso),
        .sclk    (sclk),
        .mosi    (mosi),
        .cs_n    (cs_n),
        .rx_data (rx_data),
        .busy    (busy),
        .done    (done)
    );
    // 10 ns period
    always #5 clk = ~clk;
    // First MISO bit is available before the
    // first rising edge.
    always @(negedge cs_n) begin
        if (!cs_n) begin
            miso = slave_tx_data[7];
        end
    end
    // Change MISO on falling edge.
    // Mode 0:
    // Rising edge  -> SAMPLE
    // Falling edge -> LAUNCH
    always @(negedge sclk) begin
        if (!cs_n) begin
            slave_tx_data = {
                slave_tx_data[6:0],
                1'b0
            };
            miso = slave_tx_data[7];
        end
    end
    initial begin
        clk     = 1'b0;
        reset   = 1'b1;
        start   = 1'b0;
        tx_data = 8'hA5;
        miso    = 1'b0;
        // Slave will send 3C
        slave_tx_data = 8'hA5;
        // Reset
        #20;
        reset = 1'b0;
        // Start SPI transfer
        #10;
        start = 1'b1;
        #10;
        start = 1'b0;
        // Wait until transfer is complete
        wait(done);
        // Display result
        #1;
        $display("");
        $display("====================================");
        $display("       SPI TRANSFER COMPLETE");
        $display("====================================");
        $display("TX DATA  = %h", tx_data);
        $display("RX DATA  = %h", rx_data);
        $display("BUSY     = %b", busy);
        $display("DONE     = %b", done);
        $display("====================================");
        $display("");
        // Check received data
        if (rx_data == 8'hA5)
            $display("TEST PASSED: RX DATA = A5");
        else
            $display("TEST FAILED: Expected A5, Got %h",
                     rx_data);
        #20;
        $finish;
    end
    initial begin
        $monitor(
            "TIME=%0t | RESET=%b | START=%b | CS_N=%b | SCLK=%b | MOSI=%b | MISO=%b | RX=%h | BUSY=%b | DONE=%b",
            $time,
            reset,
            start,
            cs_n,
            sclk,
            mosi,
            miso,
            rx_data,
            busy,
            done
        );
    end
    initial begin
        $dumpfile("spi_protocol.vcd");
        $dumpvars(0, spi_protocol_tb);
    end
endmodule

spi_protocol/spi_protocol.vcd
$date
	Wed Aug 19 17:56:46 2026
$end
$version
	Icarus Verilog
$end
$timescale
	1s
$end
$scope module spi_protocol_tb $end
$var wire 1 ! sclk $end
$var wire 8 " rx_data [7:0] $end
$var wire 1 # mosi $end
$var wire 1 $ done $end
$var wire 1 % cs_n $end
$var wire 1 & busy $end
$var reg 1 ' clk $end
$var reg 1 ( miso $end
$var reg 1 ) reset $end
$var reg 8 * slave_tx_data [7:0] $end
$var reg 1 + start $end
$var reg 8 , tx_data [7:0] $end
$scope module uut $end
$var wire 1 ' clk $end
$var wire 1 ( miso $end
$var wire 1 ) reset $end
$var wire 1 + start $end
$var wire 8 - tx_data [7:0] $end
$var parameter 2 . ST_ASSERT $end
$var parameter 2 / ST_DONE $end
$var parameter 2 0 ST_IDLE $end
$var parameter 2 1 ST_TRANSFER $end
$var reg 3 2 bit_cnt [2:0] $end
$var reg 1 & busy $end
$var reg 1 % cs_n $end
$var reg 1 $ done $end
$var reg 1 # mosi $end
$var reg 8 3 rx_data [7:0] $end
$var reg 8 4 rx_shift [7:0] $end
$var reg 1 ! sclk $end
$var reg 2 5 state [1:0] $end
$var reg 8 6 tx_shift [7:0] $end
$upscope $end
$upscope $end
$enddefinitions $end
$comment Show the parameter values. $end
$dumpall
b10 1
b0 0
b11 /
b1 .
$end
#0
$dumpvars
bx 6
bx 5
bx 4
bx 3
bx 2
b10100101 -
b10100101 ,
0+
b10100101 *
1)
0(
0'
x&
x%
x$
x#
bx "
x!
$end
#5
b111 2
b0 4
b0 6
0$
0&
b0 "
b0 3
1%
0#
0!
b0 5
1'
#10
0'
#15
1'
#20
0'
0)
#25
1'
#30
0'
1+
#35
1(
b1 5
1&
0%
1#
b10100101 6
1'
#40
0'
0+
#45
b10 5
1'
#50
0'
#55
b110 2
b1 4
1!
1'
#60
0'
#65
0(
b1001010 *
0#
b1001010 6
0!
1'
#70
0'
#75
b101 2
b10 4
1!
1'
#80
0'
#85
1(
b10010100 *
1#
b10010100 6
0!
1'
#90
0'
#95
b100 2
b101 4
1!
1'
#100
0'
#105
0(
b101000 *
0#
b101000 6
0!
1'
#110
0'
#115
b11 2
b1010 4
1!
1'
#120
0'
#125
b1010000 *
b1010000 6
0!
1'
#130
0'
#135
b10 2
b10100 4
1!
1'
#140
0'
#145
1(
b10100000 *
1#
b10100000 6
0!
1'
#150
0'
#155
b1 2
b101001 4
1!
1'
#160
0'
#165
0(
b1000000 *
0#
b1000000 6
0!
1'
#170
0'
#175
b0 2
b1010010 4
1!
1'
#180
0'
#185
1(
b10000000 *
b10000000 6
0!
1'
#190
0'
#195
1$
b10100101 "
b10100101 3
0&
1%
b11 5
b10100101 4
0!
1'
#200
0'
#205
b0 5
0$
1'
