spi_protocol/spi_protocol.v
`timescale 1ns/1ps

module spi_protocol (
    input  wire       clk,
    input  wire       reset,
    input  wire       start,
    input  wire [7:0] tx_data,
    input  wire       miso,

    output wire       sclk,
    output reg        mosi,
    output reg        cs_n,
    output reg [7:0]  rx_data,
    output reg        busy,
    output reg        done
);

    //============================================
    // SPI MODE 0
    //
    // CPOL = 0
    // CPHA = 0
    //
    // Rising edge  -> Sample MISO
    // Falling edge -> Change MOSI
    //============================================

    localparam ST_IDLE     = 2'd0;
    localparam ST_TRANSFER = 2'd1;
    localparam ST_DONE     = 2'd2;

    reg [1:0] state;

    reg [7:0] tx_shift;
    reg [7:0] rx_shift;

    reg [2:0] bit_cnt;
    reg       active;


    //============================================
    // SCLK = CLK
    // Same frequency
    // When SPI is inactive, SCLK stays LOW
    //============================================

    assign sclk = active ? clk : 1'b0;


    //============================================
    // START / CONTROL
    // First MOSI bit must be ready
    // before first rising edge
    //============================================

    always @(negedge clk or posedge reset) begin

        if (reset) begin

            state    <= ST_IDLE;

            tx_shift <= 8'h00;
            bit_cnt  <= 3'd7;

            mosi     <= 1'b0;
            cs_n     <= 1'b1;

            busy     <= 1'b0;
            done     <= 1'b0;

            active   <= 1'b0;

        end

        else begin

            done <= 1'b0;

            case (state)

                //====================================
                // IDLE
                //====================================

                ST_IDLE: begin

                    cs_n   <= 1'b1;
                    busy   <= 1'b0;
                    mosi   <= 1'b0;
                    active <= 1'b0;

                    if (start) begin

                        tx_shift <= tx_data;

                        bit_cnt <= 3'd7;

                        // First MOSI bit = MSB
                        mosi <= tx_data[7];

                        // Start SPI transaction
                        cs_n   <= 1'b0;
                        busy   <= 1'b1;
                        active <= 1'b1;

                        state <= ST_TRANSFER;

                    end

                end


                //====================================
                // TRANSFER
                // Falling edge -> Change MOSI
                //====================================

                ST_TRANSFER: begin

                    if (bit_cnt != 3'd0) begin

                        // Shift TX register
                        tx_shift <= {
                            tx_shift[6:0],
                            1'b0
                        };

                        // Send next bit
                        mosi <= tx_shift[6];

                    end

                end


                //====================================
                // DONE
                //====================================

                ST_DONE: begin

                    cs_n   <= 1'b1;
                    busy   <= 1'b0;
                    active <= 1'b0;
                    mosi   <= 1'b0;

                    done <= 1'b1;

                    state <= ST_IDLE;

                end


                default: begin

                    state  <= ST_IDLE;
                    cs_n   <= 1'b1;
                    busy   <= 1'b0;
                    active <= 1'b0;
                    mosi   <= 1'b0;

                end

            endcase

        end

    end


    //============================================
    // RECEIVE
    //
    // MODE 0:
    // Rising edge -> Sample MISO
    //============================================

    always @(posedge clk or posedge reset) begin

        if (reset) begin

            rx_shift <= 8'h00;
            rx_data  <= 8'h00;

        end

        else if (state == ST_TRANSFER && active) begin

            // Sample MISO
            rx_shift <= {
                rx_shift[6:0],
                miso
            };


            // Last bit?
            if (bit_cnt == 3'd0) begin

                // Store final received data
                rx_data <= {
                    rx_shift[6:0],
                    miso
                };

                // Transfer completed
                state <= ST_DONE;

            end

            else begin

                // Count received bits
                bit_cnt <= bit_cnt - 3'd1;

            end

        end

    end

endmodule

spi_protocol/spi_protocol_tb.v
`timescale 1ns/1ps

module spi_protocol_tb;

    //============================================
    // DUT INPUTS
    //============================================

    reg        clk;
    reg        reset;
    reg        start;
    reg [7:0]  tx_data;
    reg        miso;


    //============================================
    // DUT OUTPUTS
    //============================================

    wire       sclk;
    wire       mosi;
    wire       cs_n;
    wire [7:0] rx_data;
    wire       busy;
    wire       done;


    //============================================
    // DUT INSTANTIATION
    //============================================

    spi_protocol uut (

        .clk     (clk),
        .reset   (reset),
        .start   (start),
        .tx_data (tx_data),
        .miso    (miso),

        .sclk    (sclk),
        .mosi    (mosi),
        .cs_n    (cs_n),
        .rx_data (rx_data),
        .busy    (busy),
        .done    (done)

    );


    //============================================
    // 50 MHz CLOCK
    //
    // Period = 20 ns
    // Half period = 10 ns
    //============================================

    always #10 clk = ~clk;


    //============================================
    // SLAVE DATA
    //============================================

    reg [7:0] slave_tx_data;
    reg [2:0] slave_bit_cnt;


    //============================================
    // FIRST MISO BIT
    //
    // Mode 0:
    // Data must be ready before
    // the first rising edge.
    //============================================

    always @(negedge cs_n) begin

        if (!reset) begin

            // Send first bit (MSB)
            miso = slave_tx_data[7];

            // Next bit position
            slave_bit_cnt = 3'd6;

        end

    end


    //============================================
    // SLAVE OPERATION
    //
    // Mode 0:
    //
    // Falling edge -> Change next MISO bit
    // Rising edge  -> Master samples MISO
    //============================================

    always @(negedge sclk) begin

        if (!cs_n) begin

            miso = slave_tx_data[slave_bit_cnt];

            if (slave_bit_cnt != 3'd0)
                slave_bit_cnt = slave_bit_cnt - 3'd1;

        end

    end


    //============================================
    // MAIN TEST
    //============================================

    initial begin

        // Initial values
        clk     = 1'b0;
        reset   = 1'b1;
        start   = 1'b0;

        tx_data = 8'hA5;

        // Slave sends 3C
        slave_tx_data = 8'h3C;
        slave_bit_cnt = 3'd7;

        miso = 1'b0;


        //========================================
        // RESET
        //========================================

        #40;

        reset = 1'b0;


        //========================================
        // START SPI TRANSFER
        //========================================

        #10;

        start = 1'b1;

        #20;

        start = 1'b0;


        //========================================
        // WAIT FOR TRANSFER
        //========================================

        #400;


        //========================================
        // DISPLAY RESULT
        //========================================

        $display("--------------------------------");
        $display("       SPI MODE 0 RESULT");
        $display("--------------------------------");

        $display("CLK Frequency  = 50 MHz");
        $display("SCLK Frequency = 50 MHz");

        $display("Master TX = %h", tx_data);
        $display("Slave TX  = %h", slave_tx_data);
        $display("Master RX = %h", rx_data);

        $display("--------------------------------");


        // Check result

        if (rx_data == slave_tx_data)
            $display("TEST PASSED");
        else
            $display("TEST FAILED");


        #50;

        $finish;

    end


    //============================================
    // MONITOR
    //============================================

    initial begin

        $monitor(
            "TIME=%0t | CLK=%b | SCLK=%b | CS=%b | MOSI=%b | MISO=%b | RX=%h | BUSY=%b | DONE=%b",
            $time,
            clk,
            sclk,
            cs_n,
            mosi,
            miso,
            rx_data,
            busy,
            done
        );

    end


    //============================================
    // VCD FILE
    //============================================

    initial begin

        $dumpfile("spi_protocol.vcd");

        $dumpvars(0, spi_protocol_tb);

    end

endmodule

spi_protocol/spi_protocol.vcd
$date
	Tue Sep  1 17:04:13 2026
$end
$version
	Icarus Verilog
$end
$timescale
	1ps
$end
$scope module spi_protocol_tb $end
$var wire 1 ! sclk $end
$var wire 8 " rx_data [7:0] $end
$var wire 1 # mosi $end
$var wire 1 $ done $end
$var wire 1 % cs_n $end
$var wire 1 & busy $end
$var reg 1 ' clk $end
$var reg 1 ( miso $end
$var reg 1 ) reset $end
$var reg 3 * slave_bit_cnt [2:0] $end
$var reg 8 + slave_tx_data [7:0] $end
$var reg 1 , start $end
$var reg 8 - tx_data [7:0] $end
$scope module uut $end
$var wire 1 ' clk $end
$var wire 1 ( miso $end
$var wire 1 ) reset $end
$var wire 1 , start $end
$var wire 8 . tx_data [7:0] $end
$var wire 1 ! sclk $end
$var parameter 2 / ST_DONE $end
$var parameter 2 0 ST_IDLE $end
$var parameter 2 1 ST_TRANSFER $end
$var reg 1 2 active $end
$var reg 3 3 bit_cnt [2:0] $end
$var reg 1 & busy $end
$var reg 1 % cs_n $end
$var reg 1 $ done $end
$var reg 1 # mosi $end
$var reg 8 4 rx_data [7:0] $end
$var reg 8 5 rx_shift [7:0] $end
$var reg 2 6 state [1:0] $end
$var reg 8 7 tx_shift [7:0] $end
$upscope $end
$upscope $end
$enddefinitions $end
$comment Show the parameter values. $end
$dumpall
b1 1
b0 0
b10 /
$end
#0
$dumpvars
b0 7
b0 6
b0 5
b0 4
b111 3
02
b10100101 .
b10100101 -
0,
b111100 +
b111 *
1)
0(
0'
0&
1%
0$
0#
b0 "
0!
$end
#10000
1'
#20000
0'
#30000
1'
#40000
0'
0)
#50000
1'
1,
#60000
b110 *
b1 6
12
1&
0%
1#
b10100101 7
0'
#70000
b110 3
1!
1'
0,
#80000
0#
b1001010 7
b101 *
0!
0'
#90000
b101 3
1!
1'
#100000
1#
b10010100 7
b100 *
1(
0!
0'
#110000
b100 3
b1 5
1!
1'
#120000
0#
b101000 7
b11 *
0!
0'
#130000
b11 3
b11 5
1!
1'
#140000
b1010000 7
b10 *
0!
0'
#150000
b10 3
b111 5
1!
1'
#160000
1#
b10100000 7
b1 *
0!
0'
#170000
b1 3
b1111 5
1!
1'
#180000
0#
b1000000 7
b0 *
0(
0!
0'
#190000
b0 3
b11110 5
1!
1'
#200000
0!
0'
#210000
b10 6
b111100 "
b111100 4
b111100 5
1!
1'
#220000
b0 6
1$
02
0&
1%
0!
0'
#230000
1'
#240000
0$
0'
