moore_example/moore_example.v
module moore_10110(
input clk,
input reset,
input din,
output reg y);
reg [2:0]state,next_state;
parameter s0=3'b000,
s1=3'b001,
s2=3'b010,
s3=3'b011,
s4=3'b100,
s5=3'b101,
s6=3'b110,
s7=3'b111;
always@(posedge clk or posedge reset)begin
if(reset)
state<=s0;
else
state<=next_state;
end
always@(*)begin
case (state)
s0:begin
if(din)
next_state=s1;
else
next_state=s0;
end
s1:begin
if(din)
next_state = s1;
else
next_state=s2;
end
s2: begin
            if (din)
                next_state = s3;
            else
                next_state = s0;end
s3: begin
            if (din)
                next_state = s4;
            else
                next_state = s0;
end
s4: begin
            if (din)
                next_state = s1;
            else
                next_state = s5;
end
s5: begin
            if (din)
                next_state = s0;
            else
                next_state = s3;
end
default:next_state=s0;
endcase
end
always @(*) begin
    if (state == s5)
        y = 1'b1;
    else
        y = 1'b0;
end
endmodule

moore_example/moore_example_tb.v
module moore_10110_tb;
reg clk;
reg reset;
reg din;
wire y;
moore_10110 uut(.clk(clk),.reset(reset),.din(din),.y(y));
always #5 clk=~clk;
initial begin
clk=0;
reset=1;
din=0;
#10;
reset=0;
din=1;
#10;
din=0;
#10;
din=1;
#10;
din=1;
#10;
din=0;
#10;
$finish;
end
initial begin
    $dumpfile("moore_10110.vcd");
    $dumpvars;
end
initial begin
$monitor("clk=%b reset=%b din=%b y=%b",clk,reset,din,y);
end
endmodule

moore_example/moore_10110.vcd
$date
	Wed Aug 19 05:03:30 2026
$end
$version
	Icarus Verilog
$end
$timescale
	1s
$end
$scope module moore_10110_tb $end
$var wire 1 ! y $end
$var reg 1 " clk $end
$var reg 1 # din $end
$var reg 1 $ reset $end
$scope module uut $end
$var wire 1 " clk $end
$var wire 1 # din $end
$var wire 1 $ reset $end
$var parameter 3 % s0 $end
$var parameter 3 & s1 $end
$var parameter 3 ' s2 $end
$var parameter 3 ( s3 $end
$var parameter 3 ) s4 $end
$var parameter 3 * s5 $end
$var parameter 3 + s6 $end
$var parameter 3 , s7 $end
$var reg 3 - next_state [2:0] $end
$var reg 3 . state [2:0] $end
$var reg 1 ! y $end
$upscope $end
$upscope $end
$enddefinitions $end
$comment Show the parameter values. $end
$dumpall
b111 ,
b110 +
b101 *
b100 )
b11 (
b10 '
b1 &
b0 %
$end
#0
$dumpvars
b0 .
b0 -
1$
0#
0"
0!
$end
#5
1"
#10
b1 -
0"
1#
0$
#15
b1 .
1"
#20
b10 -
0"
0#
#25
b0 -
b10 .
1"
#30
b11 -
0"
1#
#35
b100 -
b11 .
1"
#40
0"
#45
b1 -
b100 .
1"
#50
b101 -
0"
0#
#55
1!
b11 -
b101 .
1"
