uart/receiver.v
module receiver #(
    parameter CLK_FREQ  = 50000000,
    parameter BAUD_RATE = 9600
)(
    input wire clk,
    input wire reset,
    input wire rx,
    output reg [7:0] data_out,
    output reg rx_valid
);
localparam CLK_PER_BIT = CLK_FREQ / BAUD_RATE;
localparam IDLE  = 2'b00;
localparam START = 2'b01;
localparam DATA  = 2'b10;
localparam STOP  = 2'b11;

reg [1:0] state;
reg [15:0] baud_count;
reg [3:0] bit_count;
reg [7:0] shift_reg;
always @(posedge clk or negedge reset) begin
    if (!reset) begin
        state      <= IDLE;
        baud_count <= 16'd0;
        bit_count  <= 4'd0;
        shift_reg  <= 8'd0;
        data_out   <= 8'd0;
        rx_valid   <= 1'b0;
    end
    else begin
        rx_valid <= 1'b0;
        case (state)

		IDLE: begin

            baud_count <= 16'd0;
            bit_count  <= 4'd0;

            if (rx == 1'b0) begin
                state      <= START;
                baud_count <= 16'd0;
            end

        end

	START: begin

            if (baud_count == (CLK_PER_BIT/2) - 1) begin
                baud_count <= 16'd0;
                if (rx == 1'b0) begin
                    state     <= DATA;
                    bit_count <= 4'd0;
                end
                else begin
                    state <= IDLE;
                end
            end
            else begin
                baud_count <= baud_count + 1'b1;
            end
        end

	DATA: begin

            if (baud_count == CLK_PER_BIT - 1) begin
                baud_count <= 16'd0;
                shift_reg[bit_count] <= rx;
                if (bit_count == 4'd7) begin
                    bit_count <= 4'd0;
                    state     <= STOP;
                end
                else begin
                    bit_count <= bit_count + 1'b1;
                end
            end
            else begin
                baud_count <= baud_count + 1'b1;
            end
        end

	STOP: begin

            if (baud_count == CLK_PER_BIT - 1) begin
                baud_count <= 16'd0;
                if (rx == 1'b1) begin
                    data_out <= shift_reg;
                    rx_valid <= 1'b1;
                end
                state <= IDLE;
            end
            else begin
                baud_count <= baud_count + 1'b1;
            end
        end
        default: begin
            state      <= IDLE;
            baud_count <= 16'd0;
            bit_count  <= 4'd0;
        end
        endcase
    end
end
endmodule

uart/tx.v
module tx #(
    parameter CLK_FREQ = 50000000,
    parameter BAUD_RATE = 9600
)(
    input clk,
    input reset,
    input ena,
    input [7:0] data_in,
    output reg tx,
    output reg busy
);
localparam CLK_PER_BIT = CLK_FREQ / BAUD_RATE;
parameter IDLE  = 2'b00;
parameter START = 2'b01;
parameter DATA  = 2'b10;
parameter STOP  = 2'b11;
reg [1:0] state, next_state;
reg [3:0] bit_count;
reg [7:0] shift_reg;
reg [15:0] baud_count;

always @(posedge clk or negedge reset) begin
    if (!reset) begin
        state      <= IDLE;
        tx         <= 1'b1;
        busy       <= 1'b0;
        baud_count <= 16'd0;
        bit_count  <= 4'd0;
        shift_reg  <= 8'd0;
    end
    else begin
        state <= next_state;
        case (state)
        IDLE: begin
            tx         <= 1'b1;
            busy       <= 1'b0;
            baud_count <= 16'd0;
            bit_count  <= 4'd0;
            if (ena) begin
                shift_reg <= data_in;
                busy      <= 1'b1;
            end
        end

	START: begin
            tx   <= 1'b0;
            busy <= 1'b1;
            if (baud_count == CLK_PER_BIT - 1) begin
                baud_count <= 16'd0;
            end
            else begin
                baud_count <= baud_count + 1'b1;
            end
        end

	DATA: begin
            tx   <= shift_reg[bit_count];
            busy <= 1'b1;
            if (baud_count == CLK_PER_BIT - 1) begin
                baud_count <= 16'd0;
                if (bit_count == 4'd7) begin
                    bit_count <= 4'd0;
                end
                else begin
                    bit_count <= bit_count + 1'b1;
                end
            end
            else begin
                baud_count <= baud_count + 1'b1;
            end
        end

	STOP: begin
            tx   <= 1'b1;
            busy <= 1'b1;
            if (baud_count == CLK_PER_BIT - 1) begin
                baud_count <= 16'd0;
                busy       <= 1'b0;
            end
            else begin
                baud_count <= baud_count + 1'b1;
            end
        end
        default: begin
            state <= IDLE;
            tx    <= 1'b1;
            busy  <= 1'b0;
        end
        endcase
    end
end

always @(*) begin
    next_state = state;
    case (state)
    IDLE: begin
        if (ena)
            next_state = START;
    end

    START: begin
        if (baud_count == CLK_PER_BIT - 1)
            next_state = DATA;
    end

    DATA: begin
        if (baud_count == CLK_PER_BIT - 1) begin
            if (bit_count == 4'd7)
                next_state = STOP;
            else
                next_state = DATA;
        end
    end

    STOP: begin
        if (baud_count == CLK_PER_BIT - 1)
            next_state = IDLE;
    end
    default: begin
        next_state = IDLE;
    end
    endcase
end
endmodule

uart/topmodule.v
module topmodule #(
    parameter CLK_FREQ  = 50000000,
    parameter BAUD_RATE = 9600
) (
    input  wire clk,
    input  wire reset,
    output wire tx_pin,
    input  wire rx_pin,
    input  wire tx_start,
    input  wire [7:0]  tx_data_in,
    output wire tx_busy,
    output wire [7:0]  rx_data_out,
    output wire rx_valid
);

tx #(
    .CLK_FREQ  (CLK_FREQ),
    .BAUD_RATE (BAUD_RATE)
) u_tx (
    .clk (clk),
    .reset (reset),
    .ena (tx_start),
    .data_in (tx_data_in),
    .tx (tx_pin),
    .busy (tx_busy)
);

receiver #(
    .CLK_FREQ  (CLK_FREQ),
    .BAUD_RATE (BAUD_RATE)
) receiver (
    .clk       (clk),
    .reset     (reset),
    .rx        (rx_pin),
    .data_out  (rx_data_out),
    .rx_valid  (rx_valid)
);
endmodule

uart/tb.v
`timescale 1ns/1ps

module topmodule_tb;

reg clk;
reg reset;

reg tx_start;
reg [7:0] tx_data_in;

wire tx_pin;
wire rx_pin;
wire tx_busy;

wire [7:0] rx_data_out;
wire rx_valid;


//========================================
// TX -> RX LOOPBACK
//========================================

assign rx_pin = tx_pin;


//========================================
// DUT
//========================================

topmodule #(
    .CLK_FREQ  (50000000),
    .BAUD_RATE (9600)
) uut (
    .clk         (clk),
    .reset       (reset),

    .tx_pin      (tx_pin),
    .rx_pin      (rx_pin),

    .tx_start    (tx_start),
    .tx_data_in  (tx_data_in),
    .tx_busy     (tx_busy),

    .rx_data_out (rx_data_out),
    .rx_valid    (rx_valid)
);


//========================================
// 50 MHz CLOCK
//========================================

always #10 clk = ~clk;


//========================================
// TEST
//========================================

initial begin

    $dumpfile("uart.vcd");
    $dumpvars(0, topmodule_tb);

    clk        = 1'b0;
    reset      = 1'b0;
    tx_start   = 1'b0;
    tx_data_in = 8'h00;

    // Reset
    #100;
    reset = 1'b1;

    #100;

    //====================================
    // SEND A5
    //====================================

    tx_data_in = 8'hA5;
    tx_start   = 1'b1;

    #20;
    tx_start   = 1'b0;

    $display("TX Started");
    $display("TX Data = %h", tx_data_in);


    //====================================
    // WAIT FOR RX VALID
    //====================================

    @(posedge rx_valid);

    $display("RX Valid = %b", rx_valid);
    $display("RX Data  = %h", rx_data_out);


    //====================================
    // CHECK RESULT
    //====================================

    if (rx_data_out == 8'hA5)
        $display("TEST PASSED");
    else
        $display("TEST FAILED");

    #100;
    $finish;
end
endmodule

uart/uart.vcd
$date
	Wed Sep 16 12:43:59 2026
$end
$version
	Icarus Verilog
$end
$timescale
	1ps
$end
$scope module topmodule_tb $end
$var wire 1 ! rx_pin $end
$var wire 1 " tx_pin $end
$var wire 1 # tx_busy $end
$var wire 1 $ rx_valid $end
$var wire 8 % rx_data_out [7:0] $end
$var reg 1 & clk $end
$var reg 1 ' reset $end
$var reg 8 ( tx_data_in [7:0] $end
$var reg 1 ) tx_start $end
$scope module uut $end
$var wire 1 & clk $end
$var wire 1 ' reset $end
$var wire 1 ! rx_pin $end
$var wire 8 * tx_data_in [7:0] $end
$var wire 1 ) tx_start $end
$var wire 1 " tx_pin $end
$var wire 1 # tx_busy $end
$var wire 1 $ rx_valid $end
$var wire 8 + rx_data_out [7:0] $end
$var parameter 32 , BAUD_RATE $end
$var parameter 32 - CLK_FREQ $end
$scope module receiver $end
$var wire 1 & clk $end
$var wire 1 ' reset $end
$var wire 1 ! rx $end
$var parameter 32 . BAUD_RATE $end
$var parameter 32 / CLK_FREQ $end
$var parameter 32 0 CLK_PER_BIT $end
$var parameter 2 1 DATA $end
$var parameter 2 2 IDLE $end
$var parameter 2 3 START $end
$var parameter 2 4 STOP $end
$var reg 16 5 baud_count [15:0] $end
$var reg 4 6 bit_count [3:0] $end
$var reg 8 7 data_out [7:0] $end
$var reg 1 $ rx_valid $end
$var reg 8 8 shift_reg [7:0] $end
$var reg 2 9 state [1:0] $end
$upscope $end
$scope module u_tx $end
$var wire 1 & clk $end
$var wire 8 : data_in [7:0] $end
$var wire 1 ) ena $end
$var wire 1 ' reset $end
$var parameter 32 ; BAUD_RATE $end
$var parameter 32 < CLK_FREQ $end
$var parameter 32 = CLK_PER_BIT $end
$var parameter 2 > DATA $end
$var parameter 2 ? IDLE $end
$var parameter 2 @ START $end
$var parameter 2 A STOP $end
$var reg 16 B baud_count [15:0] $end
$var reg 4 C bit_count [3:0] $end
$var reg 1 # busy $end
$var reg 2 D next_state [1:0] $end
$var reg 8 E shift_reg [7:0] $end
$var reg 2 F state [1:0] $end
$var reg 1 " tx $end
$upscope $end
$upscope $end
$upscope $end
$enddefinitions $end
$comment Show the parameter values. $end
$dumpall
b11 A
b1 @
b0 ?
b10 >
b1010001011000 =
b10111110101111000010000000 <
b10010110000000 ;
b11 4
b1 3
b0 2
b10 1
b1010001011000 0
b10111110101111000010000000 /
b10010110000000 .
b10111110101111000010000000 -
b10010110000000 ,
$end
#0
$dumpvars
b0 F
b0 E
b0 D
b0 C
b0 B
b0 :
b0 9
b0 8
b0 7
b0 6
b0 5
b0 +
b0 *
0)
b0 (
0'
0&
b0 %
0$
0#
1"
1!
$end
#10000
1&
#20000
0&
#30000
1&
#40000
0&
#50000
1&
#60000
0&
#70000
1&
#80000
0&
#90000
1&
#100000
0&
1'
#110000
1&
#120000
0&
#130000
1&
#140000
0&
#150000
1&
#160000
0&
#170000
1&
#180000
0&
#190000
1&
#200000
b1 D
0&
1)
b10100101 (
b10100101 *
b10100101 :
#210000
1#
b10100101 E
b1 F
1&
#220000
0&
0)
#230000
b1 B
0!
0"
1&
#240000
0&
#250000
b1 9
b10 B
1&
#260000
0&
#270000
b11 B
b1 5
1&
#280000
0&
#290000
b10 5
b100 B
1&
#300000
0&
#310000
b101 B
b11 5
1&
#320000
0&
#330000
b100 5
b110 B
1&
#340000
0&
#350000
b111 B
b101 5
1&
#360000
0&
#370000
b110 5
b1000 B
1&
#380000
0&
#390000
b1001 B
b111 5
1&
#400000
0&
#410000
b1000 5
b1010 B
1&
#420000
0&
#430000
b1011 B
b1001 5
1&
#440000
0&
#450000
b1010 5
b1100 B
1&
#460000
0&
#470000
b1101 B
b1011 5
1&
#480000
0&
#490000
b1100 5
b1110 B
1&
#500000
0&
#510000
b1111 B
b1101 5
1&
#520000
0&
#530000
b1110 5
b10000 B
1&
#540000
0&
#550000
b10001 B
b1111 5
1&
#560000
0&
#570000
b10000 5
b10010 B
1&
#580000
0&
#590000
b10011 B
b10001 5
1&
#600000
0&
#610000
b10010 5
b10100 B
1&
#620000
0&
#630000
b10101 B
b10011 5
1&
#640000
0&
#650000
b10100 5
b10110 B
1&
#660000
0&
#670000
b10111 B
b10101 5
1&
#680000
0&
#690000
b10110 5
b11000 B
1&
#700000
0&
#710000
b11001 B
b10111 5
1&
#720000
0&
#730000
b11000 5
b11010 B
1&
#740000
0&
#750000
b11011 B
b11001 5
1&
#760000
0&
#770000
b11010 5
b11100 B
1&
#780000
0&
#790000
b11101 B
b11011 5
1&
#800000
0&
#810000
b11100 5
b11110 B
1&
#820000
0&
#830000
b11111 B
b11101 5
1&
#840000
0&
#850000
b11110 5
b100000 B
1&
#860000
0&
#870000
b100001 B
b11111 5
1&
#880000
0&
#890000
b100000 5
b100010 B
1&
#900000
0&
#910000
b100011 B
b100001 5
1&
#920000
0&
#930000
b100010 5
b100100 B
1&
#940000
0&
#950000
b100101 B
b100011 5
1&
#960000
0&
#970000
b100100 5
b100110 B
1&
#980000
0&
#990000
b100111 B
b100101 5
1&
#1000000
0&
#1010000
b100110 5
b101000 B
1&
#1020000
0&
#1030000
b101001 B
b100111 5
1&
#1040000
0&
#1050000
b101000 5
b101010 B
1&
#1060000
0&
#1070000
b101011 B
b101001 5
1&
#1080000
0&
#1090000
b101010 5
b101100 B
1&
#1100000
0&
#1110000
b101101 B
b101011 5
1&
#1120000
0&
#1130000
b101100 5
b101110 B
1&
#1140000
0&
#1150000
b101111 B
b101101 5
1&
#1160000
0&
#1170000
b101110 5
b110000 B
1&
#1180000
0&
#1190000
b110001 B
b101111 5
1&
#1200000
0&
#1210000
b110000 5
b110010 B
1&
#1220000
0&
#1230000
b110011 B
b110001 5
1&
#1240000
0&
#1250000
b110010 5
b110100 B
1&
#1260000
0&
#1270000
b110101 B
b110011 5
1&
#1280000
0&
#1290000
b110100 5
b110110 B
1&
#1300000
0&
#1310000
b110111 B
b110101 5
1&
#1320000
0&
#1330000
b110110 5
b111000 B
1&
#1340000
0&
#1350000
b111001 B
b110111 5
1&
#1360000
0&
#1370000
b111000 5
b111010 B
1&
#1380000
0&
#1390000
b111011 B
b111001 5
1&
#1400000
0&
#1410000
b111010 5
b111100 B
1&
#1420000
0&
#1430000
b111101 B
b111011 5
1&
#1440000
0&
#1450000
b111100 5
b111110 B
1&
#1460000
0&
#1470000
b111111 B
b111101 5
1&
#1480000
0&
#1490000
b111110 5
b1000000 B
1&
#1500000
0&
#1510000
b1000001 B
b111111 5
1&
#1520000
0&
#1530000
b1000000 5
b1000010 B
1&
#1540000
0&
#1550000
b1000011 B
b1000001 5
1&
#1560000
0&
#1570000
b1000010 5
b1000100 B
1&
#1580000
0&
#1590000
b1000101 B
b1000011 5
1&
#1600000
0&
#1610000
b1000100 5
b1000110 B
1&
#1620000
0&
#1630000
b1000111 B
b1000101 5
1&
#1640000
0&
#1650000
b1000110 5
b1001000 B
1&
#1660000
0&
#1670000
b1001001 B
b1000111 5
1&
#1680000
0&
#1690000
b1001000 5
b1001010 B
1&
#1700000
0&
#1710000
b1001011 B
b1001001 5
1&
#1720000
0&
#1730000
b1001010 5
b1001100 B
1&
#1740000
0&
#1750000
b1001101 B
b1001011 5
1&
#1760000
0&
#1770000
b1001100 5
b1001110 B
1&
#1780000
0&
#1790000
b1001111 B
b1001101 5
1&
#1800000
0&
#1810000
b1001110 5
b1010000 B
1&
#1820000
0&
#1830000
b1010001 B
b1001111 5
1&
#1840000
0&
#1850000
b1010000 5
b1010010 B
1&
#1860000
0&
#1870000
b1010011 B
b1010001 5
1&
#1880000
0&
#1890000
b1010010 5
b1010100 B
1&
#1900000
0&
#1910000
b1010101 B
b1010011 5
1&
#1920000
0&
#1930000
b1010100 5
b1010110 B
1&
#1940000
0&
#1950000
b1010111 B
b1010101 5
1&
#1960000
0&
#1970000
b1010110 5
b1011000 B
1&
#1980000
0&
#1990000
b1011001 B
b1010111 5
1&
#2000000
0&
#2010000
b1011000 5
b1011010 B
1&
#2020000
0&
#2030000
b1011011 B
b1011001 5
1&
#2040000
0&
#2050000
b1011010 5
b1011100 B
1&
#2060000
0&
#2070000
b1011101 B
b1011011 5
1&
#2080000
0&
#2090000
b1011100 5
b1011110 B
1&
#2100000
0&
#2110000
b1011111 B
b1011101 5
1&
#2120000
0&
#2130000
b1011110 5
b1100000 B
1&
#2140000
0&
#2150000
b1100001 B
b1011111 5
1&
#2160000
0&
#2170000
b1100000 5
b1100010 B
1&
#2180000
0&
#2190000
b1100011 B
b1100001 5
1&
#2200000
0&
#2210000
b1100010 5
b1100100 B
1&
#2220000
0&
#2230000
b1100101 B
b1100011 5
1&
#2240000
0&
#2250000
b1100100 5
b1100110 B
1&
#2260000
0&
#2270000
b1100111 B
b1100101 5
1&
#2280000
0&
#2290000
b1100110 5
b1101000 B
1&
#2300000
0&
#2310000
b1101001 B
b1100111 5
1&
#2320000
0&
#2330000
b1101000 5
b1101010 B
1&
#2340000
0&
#2350000
b1101011 B
b1101001 5
1&
#2360000
0&
#2370000
b1101010 5
b1101100 B
1&
#2380000
0&
#2390000
b1101101 B
b1101011 5
1&
#2400000
0&
#2410000
b1101100 5
b1101110 B
1&
#2420000
0&
#2430000
b1101111 B
b1101101 5
1&
#2440000
0&
#2450000
b1101110 5
b1110000 B
1&
#2460000
0&
#2470000
b1110001 B
b1101111 5
1&
#2480000
0&
#2490000
b1110000 5
b1110010 B
1&
#2500000
0&
#2510000
b1110011 B
b1110001 5
1&
#2520000
0&
#2530000
b1110010 5
b1110100 B
1&
#2540000
0&
#2550000
b1110101 B
b1110011 5
1&
#2560000
0&
#2570000
b1110100 5
b1110110 B
1&
#2580000
0&
#2590000
b1110111 B
b1110101 5
1&
#2600000
0&
#2610000
b1110110 5
b1111000 B
1&
#2620000
0&
#2630000
b1111001 B
b1110111 5
1&
#2640000
0&
#2650000
b1111000 5
b1111010 B
1&
#2660000
0&
#2670000
b1111011 B
b1111001 5
1&
#2680000
0&
#2690000
b1111010 5
b1111100 B
1&
#2700000
0&
#2710000
b1111101 B
b1111011 5
1&
#2720000
0&
#2730000
b1111100 5
b1111110 B
1&
#2740000
0&
#2750000
b1111111 B
b1111101 5
1&
#2760000
0&
#2770000
b1111110 5
b10000000 B
1&
#2780000
0&
#2790000
b10000001 B
b1111111 5
1&
#2800000
0&
#2810000
b10000000 5
b10000010 B
1&
#2820000
0&
#2830000
b10000011 B
b10000001 5
1&
#2840000
0&
#2850000
b10000010 5
b10000100 B
1&
#2860000
0&
#2870000
b10000101 B
b10000011 5
1&
#2880000
0&
#2890000
b10000100 5
b10000110 B
1&
#2900000
0&
#2910000
b10000111 B
b10000101 5
1&
#2920000
0&
#2930000
b10000110 5
b10001000 B
1&
#2940000
0&
#2950000
b10001001 B
b10000111 5
1&
#2960000
0&
#2970000
b10001000 5
b10001010 B
1&
#2980000
0&
#2990000
b10001011 B
b10001001 5
1&
#3000000
0&
#3010000
b10001010 5
b10001100 B
1&
#3020000
0&
#3030000
b10001101 B
b10001011 5
1&
#3040000
0&
#3050000
b10001100 5
b10001110 B
1&
#3060000
0&
#3070000
b10001111 B
b10001101 5
1&
#3080000
0&
#3090000
b10001110 5
b10010000 B
1&
#3100000
0&
#3110000
b10010001 B
b10001111 5
1&
#3120000
0&
#3130000
b10010000 5
b10010010 B
1&
#3140000
0&
#3150000
b10010011 B
b10010001 5
1&
#3160000
0&
#3170000
b10010010 5
b10010100 B
1&
#3180000
0&
#3190000
b10010101 B
b10010011 5
1&
#3200000
0&
#3210000
b10010100 5
b10010110 B
1&
#3220000
0&
#3230000
b10010111 B
b10010101 5
1&
#3240000
0&
#3250000
b10010110 5
b10011000 B
1&
#3260000
0&
#3270000
b10011001 B
b10010111 5
1&
#3280000
0&
#3290000
b10011000 5
b10011010 B
1&
#3300000
0&
#3310000
b10011011 B
b10011001 5
1&
#3320000
0&
#3330000
b10011010 5
b10011100 B
1&
#3340000
0&
#3350000
b10011101 B
b10011011 5
1&
#3360000
0&
#3370000
b10011100 5
b10011110 B
1&
#3380000
0&
#3390000
b10011111 B
b10011101 5
1&
#3400000
0&
#3410000
b10011110 5
b10100000 B
1&
#3420000
0&
#3430000
b10100001 B
b10011111 5
1&
#3440000
0&
#3450000
b10100000 5
b10100010 B
1&
#3460000
0&
#3470000
b10100011 B
b10100001 5
1&
#3480000
0&
#3490000
b10100010 5
b10100100 B
1&
#3500000
0&
#3510000
b10100101 B
b10100011 5
1&
#3520000
0&
#3530000
b10100100 5
b10100110 B
1&
#3540000
0&
#3550000
b10100111 B
b10100101 5
1&
#3560000
0&
#3570000
b10100110 5
b10101000 B
1&
#3580000
0&
#3590000
b10101001 B
b10100111 5
1&
#3600000
0&
#3610000
b10101000 5
b10101010 B
1&
#3620000
0&
#3630000
b10101011 B
b10101001 5
1&
#3640000
0&
#3650000
b10101010 5
b10101100 B
1&
#3660000
0&
#3670000
b10101101 B
b10101011 5
1&
#3680000
0&
#3690000
b10101100 5
b10101110 B
1&
#3700000
0&
#3710000
b10101111 B
b10101101 5
1&
#3720000
0&
#3730000
b10101110 5
b10110000 B
1&
#3740000
0&
#3750000
b10110001 B
b10101111 5
1&
#3760000
0&
#3770000
b10110000 5
b10110010 B
1&
#3780000
0&
#3790000
b10110011 B
b10110001 5
1&
#3800000
0&
#3810000
b10110010 5
b10110100 B
1&
#3820000
0&
#3830000
b10110101 B
b10110011 5
1&
#3840000
0&
#3850000
b10110100 5
b10110110 B
1&
#3860000
0&
#3870000
b10110111 B
b10110101 5
1&
#3880000
0&
#3890000
b10110110 5
b10111000 B
1&
#3900000
0&
#3910000
b10111001 B
b10110111 5
1&
#3920000
0&
#3930000
b10111000 5
b10111010 B
1&
#3940000
0&
#3950000
b10111011 B
b10111001 5
1&
#3960000
0&
#3970000
b10111010 5
b10111100 B
1&
#3980000
0&
#3990000
b10111101 B
b10111011 5
1&
#4000000
0&
#4010000
b10111100 5
b10111110 B
1&
#4020000
0&
#4030000
b10111111 B
b10111101 5
1&
#4040000
0&
#4050000
b10111110 5
b11000000 B
1&
#4060000
0&
#4070000
b11000001 B
b10111111 5
1&
#4080000
0&
#4090000
b11000000 5
b11000010 B
1&
#4100000
0&
#4110000
b11000011 B
b11000001 5
1&
#4120000
0&
#4130000
b11000010 5
b11000100 B
1&
#4140000
0&
#4150000
b11000101 B
b11000011 5
1&
#4160000
0&
#4170000
b11000100 5
b11000110 B
1&
#4180000
0&
#4190000
b11000111 B
b11000101 5
1&
#4200000
0&
#4210000
b11000110 5
b11001000 B
1&
#4220000
0&
#4230000
b11001001 B
b11000111 5
1&
#4240000
0&
#4250000
b11001000 5
b11001010 B
1&
#4260000
0&
#4270000
b11001011 B
b11001001 5
1&
#4280000
0&
#4290000
b11001010 5
b11001100 B
1&
#4300000
0&
#4310000
b11001101 B
b11001011 5
1&
#4320000
0&
#4330000
b11001100 5
b11001110 B
1&
#4340000
0&
#4350000
b11001111 B
b11001101 5
1&
#4360000
0&
#4370000
b11001110 5
b11010000 B
1&
#4380000
0&
#4390000
b11010001 B
b11001111 5
1&
#4400000
0&
#4410000
b11010000 5
b11010010 B
1&
#4420000
0&
#4430000
b11010011 B
b11010001 5
1&
#4440000
0&
#4450000
b11010010 5
b11010100 B
1&
#4460000
0&
#4470000
b11010101 B
b11010011 5
1&
#4480000
0&
#4490000
b11010100 5
b11010110 B
1&
#4500000
0&
#4510000
b11010111 B
b11010101 5
1&
#4520000
0&
#4530000
b11010110 5
b11011000 B
1&
#4540000
0&
#4550000
b11011001 B
b11010111 5
1&
#4560000
0&
#4570000
b11011000 5
b11011010 B
1&
#4580000
0&
#4590000
b11011011 B
b11011001 5
1&
#4600000
0&
#4610000
b11011010 5
b11011100 B
1&
#4620000
0&
#4630000
b11011101 B
b11011011 5
1&
#4640000
0&
#4650000
b11011100 5
b11011110 B
1&
#4660000
0&
#4670000
b11011111 B
b11011101 5
1&
#4680000
0&
#4690000
b11011110 5
b11100000 B
1&
#4700000
0&
#4710000
b11100001 B
b11011111 5
1&
#4720000
0&
#4730000
b11100000 5
b11100010 B
1&
#4740000
0&
#4750000
b11100011 B
b11100001 5
1&
#4760000
0&
#4770000
b11100010 5
b11100100 B
1&
#4780000
0&
#4790000
b11100101 B
b11100011 5
1&
#4800000
0&
#4810000
b11100100 5
b11100110 B
1&
#4820000
0&
#4830000
b11100111 B
b11100101 5
1&
#4840000
0&
#4850000
b11100110 5
b11101000 B
1&
#4860000
0&
#4870000
b11101001 B
b11100111 5
1&
#4880000
0&
#4890000
b11101000 5
b11101010 B
1&
#4900000
0&
#4910000
b11101011 B
b11101001 5
1&
#4920000
0&
#4930000
b11101010 5
b11101100 B
1&
#4940000
0&
#4950000
b11101101 B
b11101011 5
1&
#4960000
0&
#4970000
b11101100 5
b11101110 B
1&
#4980000
0&
#4990000
b11101111 B
b11101101 5
1&
#5000000
0&
#5010000
b11101110 5
b11110000 B
1&
#5020000
0&
#5030000
b11110001 B
b11101111 5
1&
#5040000
0&
#5050000
b11110000 5
b11110010 B
1&
#5060000
0&
#5070000
b11110011 B
b11110001 5
1&
#5080000
0&
#5090000
b11110010 5
b11110100 B
1&
#5100000
0&
#5110000
b11110101 B
b11110011 5
1&
#5120000
0&
#5130000
b11110100 5
b11110110 B
1&
#5140000
0&
#5150000
b11110111 B
b11110101 5
1&
#5160000
0&
#5170000
b11110110 5
b11111000 B
1&
#5180000
0&
#5190000
b11111001 B
b11110111 5
1&
#5200000
0&
#5210000
b11111000 5
b11111010 B
1&
#5220000
0&
#5230000
b11111011 B
b11111001 5
1&
#5240000
0&
#5250000
b11111010 5
b11111100 B
1&
#5260000
0&
#5270000
b11111101 B
b11111011 5
1&
#5280000
0&
#5290000
b11111100 5
b11111110 B
1&
#5300000
0&
#5310000
b11111111 B
b11111101 5
1&
#5320000
0&
#5330000
b11111110 5
b100000000 B
1&
#5340000
0&
#5350000
b100000001 B
b11111111 5
1&
#5360000
0&
#5370000
b100000000 5
b100000010 B
1&
#5380000
0&
#5390000
b100000011 B
b100000001 5
1&
#5400000
0&
#5410000
b100000010 5
b100000100 B
1&
#5420000
0&
#5430000
b100000101 B
b100000011 5
1&
#5440000
0&
#5450000
b100000100 5
b100000110 B
1&
#5460000
0&
#5470000
b100000111 B
b100000101 5
1&
#5480000
0&
#5490000
b100000110 5
b100001000 B
1&
#5500000
0&
#5510000
b100001001 B
b100000111 5
1&
#5520000
0&
#5530000
b100001000 5
b100001010 B
1&
#5540000
0&
#5550000
b100001011 B
b100001001 5
1&
#5560000
0&
#5570000
b100001010 5
b100001100 B
1&
#5580000
0&
#5590000
b100001101 B
b100001011 5
1&
#5600000
0&
#5610000
b100001100 5
b100001110 B
1&
#5620000
0&
#5630000
b100001111 B
b100001101 5
1&
#5640000
0&
#5650000
b100001110 5
b100010000 B
1&
#5660000
0&
#5670000
b100010001 B
b100001111 5
1&
#5680000
0&
#5690000
b100010000 5
b100010010 B
1&
#5700000
0&
#5710000
b100010011 B
b100010001 5
1&
#5720000
0&
#5730000
b100010010 5
b100010100 B
1&
#5740000
0&
#5750000
b100010101 B
b100010011 5
1&
#5760000
0&
#5770000
b100010100 5
b100010110 B
1&
#5780000
0&
#5790000
b100010111 B
b100010101 5
1&
#5800000
0&
#5810000
b100010110 5
b100011000 B
1&
#5820000
0&
#5830000
b100011001 B
b100010111 5
1&
#5840000
0&
#5850000
b100011000 5
b100011010 B
1&
#5860000
0&
#5870000
b100011011 B
b100011001 5
1&
#5880000
0&
#5890000
b100011010 5
b100011100 B
1&
#5900000
0&
#5910000
b100011101 B
b100011011 5
1&
#5920000
0&
#5930000
b100011100 5
b100011110 B
1&
#5940000
0&
#5950000
b100011111 B
b100011101 5
1&
#5960000
0&
#5970000
b100011110 5
b100100000 B
1&
#5980000
0&
#5990000
b100100001 B
b100011111 5
1&
#6000000
0&
#6010000
b100100000 5
b100100010 B
1&
#6020000
0&
#6030000
b100100011 B
b100100001 5
1&
#6040000
0&
#6050000
b100100010 5
b100100100 B
1&
#6060000
0&
#6070000
b100100101 B
b100100011 5
1&
#6080000
0&
#6090000
b100100100 5
b100100110 B
1&
#6100000
0&
#6110000
b100100111 B
b100100101 5
1&
#6120000
0&
#6130000
b100100110 5
b100101000 B
1&
#6140000
0&
#6150000
b100101001 B
b100100111 5
1&
#6160000
0&
#6170000
b100101000 5
b100101010 B
1&
#6180000
0&
#6190000
b100101011 B
b100101001 5
1&
#6200000
0&
#6210000
b100101010 5
b100101100 B
1&
#6220000
0&
#6230000
b100101101 B
b100101011 5
1&
#6240000
0&
#6250000
b100101100 5
b100101110 B
1&
#6260000
0&
#6270000
b100101111 B
b100101101 5
1&
#6280000
0&
#6290000
b100101110 5
b100110000 B
1&
#6300000
0&
#6310000
b100110001 B
b100101111 5
1&
#6320000
0&
#6330000
b100110000 5
b100110010 B
1&
#6340000
0&
#6350000
b100110011 B
b100110001 5
1&
#6360000
0&
#6370000
b100110010 5
b100110100 B
1&
#6380000
0&
#6390000
b100110101 B
b100110011 5
1&
#6400000
0&
#6410000
b100110100 5
b100110110 B
1&
#6420000
0&
#6430000
b100110111 B
b100110101 5
1&
#6440000
0&
#6450000
b100110110 5
b100111000 B
1&
#6460000
0&
#6470000
b100111001 B
b100110111 5
1&
#6480000
0&
#6490000
b100111000 5
b100111010 B
1&
#6500000
0&
#6510000
b100111011 B
b100111001 5
1&
#6520000
0&
#6530000
b100111010 5
b100111100 B
1&
#6540000
0&
#6550000
b100111101 B
b100111011 5
1&
#6560000
0&
#6570000
b100111100 5
b100111110 B
1&
#6580000
0&
#6590000
b100111111 B
b100111101 5
1&
#6600000
0&
#6610000
b100111110 5
b101000000 B
1&
#6620000
0&
#6630000
b101000001 B
b100111111 5
1&
#6640000
0&
#6650000
b101000000 5
b101000010 B
1&
#6660000
0&
#6670000
b101000011 B
b101000001 5
1&
#6680000
0&
#6690000
b101000010 5
b101000100 B
1&
#6700000
0&
#6710000
b101000101 B
b101000011 5
1&
#6720000
0&
#6730000
b101000100 5
b101000110 B
1&
#6740000
0&
#6750000
b101000111 B
b101000101 5
1&
#6760000
0&
#6770000
b101000110 5
b101001000 B
1&
#6780000
0&
#6790000
b101001001 B
b101000111 5
1&
#6800000
0&
#6810000
b101001000 5
b101001010 B
1&
#6820000
0&
#6830000
b101001011 B
b101001001 5
1&
#6840000
0&
#6850000
b101001010 5
b101001100 B
1&
#6860000
0&
#6870000
b101001101 B
b101001011 5
1&
#6880000
0&
#6890000
b101001100 5
b101001110 B
1&
#6900000
0&
#6910000
b101001111 B
b101001101 5
1&
#6920000
0&
#6930000
b101001110 5
b101010000 B
1&
#6940000
0&
#6950000
b101010001 B
b101001111 5
1&
#6960000
0&
#6970000
b101010000 5
b101010010 B
1&
#6980000
0&
#6990000
b101010011 B
b101010001 5
1&
#7000000
0&
#7010000
b101010010 5
b101010100 B
1&
#7020000
0&
#7030000
b101010101 B
b101010011 5
1&
#7040000
0&
#7050000
b101010100 5
b101010110 B
1&
#7060000
0&
#7070000
b101010111 B
b101010101 5
1&
#7080000
0&
